[1,["ecpdLyjvZBwrvm+cedCcQy","08NXWVw0lM2KGsaqVfemFn","18I48ZiM9JjIactF1xeIdq","2adSSn4vBLvJfaGAEHBiCT","b8dFyWrDxIi4uiZQd852Z4","57KcT5c4lBNatXlBk61v+t","e7NeKdfmJINLaMFO/o3J5/","81uCUowOFAP7TXcNUEn9KL","e1hdnb5j9B54OjV1/qWy3K","0ciw58f19HeKTjrtMubWaV"],["node","_spriteFrame","_textureSetter","_parent","p_pfbHead","root","p_nodeSystem","p_nodeOther","p_nodeOwn","data"],[["cc.Node",["_name","_active","_prefab","_contentSize","_components","_anchorPoint","_trs","_children","_parent"],1,4,5,9,5,7,2,1],"cc.SpriteFrame",["cc.Node",["_name","_active","_parent","_components","_prefab","_children","_contentSize","_color","_anchorPoint","_trs"],1,1,2,4,2,5,5,5,7],["cc.Label",["_fontSize","_lineHeight","_N$verticalAlign","_N$horizontalAlign","_N$cacheMode","_string","node","_materials"],-3,1,3],["cc.Node",["_name","_active","_parent","_components","_prefab","_contentSize","_color","_anchorPoint","_children","_trs"],1,1,12,4,5,5,5,2,7],["cc.Sprite",["_sizeMode","_type","_isTrimmedMode","node","_materials","_spriteFrame"],0,1,3,6],["cc.Layout",["_resize","_N$layoutType","_N$spacingX","_N$paddingLeft","_N$paddingRight","_N$paddingTop","_N$paddingBottom","_N$horizontalDirection","node","_layoutSize"],-5,1,5],["cc.PrefabInfo",["fileId","root"],2,1],["cc.RichText",["_N$string","_N$fontSize","_N$lineHeight","_N$handleTouchEvent","_N$horizontalAlign","node"],-2,1],["cc.Prefab",["_name"],2],["ecb37cxAYNKLam1DmLf7mVL",["node","p_nodeOwn","p_nodeOther","p_nodeSystem"],3,1,1,1,1],["cc.LabelOutline",["_width","node","_color"],2,1,5],["5b769xLvXtM3qE9yTs1tpCS",["node","p_nodeHead","p_labServer","p_labName","p_nodeTx","p_labTx","p_nodeShare","p_rtxGeneral","p_nodeCheck","p_nodeJoin"],3,1,1,1,1,1,1,1,1,1,1],["bb715J7niRC+ZVrElWC9MBY",["node","p_labTx"],3,1,1]],[[7,0,1,2],[2,0,2,3,4,7,6,8,9,2],[6,0,3,4,5,6,8,9,6],[0,0,8,4,2,3,5,6,2],[5,1,0,2,3,4,5,4],[5,0,2,3,4,5,3],[0,0,1,8,7,4,2,3,5,6,3],[0,0,8,7,4,2,3,5,6,2],[0,0,8,2,3,6,2],[11,0,1,2,2],[3,0,1,2,6,7,4],[3,0,1,3,2,4,6,7,6],[3,0,1,3,2,6,7,5],[12,0,1,2,3,4,5,6,7,8,9,1],[9,0,2],[0,0,7,4,2,3,5,2],[0,0,1,7,4,2,3,5,6,3],[0,0,7,4,2,3,5,6,2],[2,0,1,2,5,3,4,3],[2,0,2,5,3,4,2],[2,0,2,3,4,6,2],[4,0,1,2,8,3,4,5,3],[4,0,2,3,4,6,5,7,2],[4,0,2,3,4,6,5,7,9,2],[10,0,1,2,3,1],[7,1,1],[5,1,0,3,4,3],[6,0,1,2,7,8,9,5],[6,0,1,2,8,9,4],[3,5,0,1,3,2,4,6,7,7],[8,0,4,1,2,3,5,6],[8,0,1,2,3,5,5],[13,0,1,1]],[[[{"name":"frame_dhk01","rect":[0,0,34,57],"offset":[0,0],"originalSize":[34,57],"capInsets":[8,8,16,8]}],[1],0,[0],[2],[6]],[[{"name":"txt_ltdjck_lang","rect":[0,0,97,26],"offset":[0,0],"originalSize":[97,26],"capInsets":[0,0,0,0]}],[1],0,[0],[2],[7]],[[{"name":"txt_ltdjjr_lang","rect":[0,0,97,26],"offset":[0,0],"originalSize":[97,26],"capInsets":[0,0,0,0]}],[1],0,[0],[2],[8]],[[[14,"chat_item"],[15,"chat_item",[-6,-7,-8],[[24,-5,-4,-3,-2]],[25,-1],[5,680,140],[0,0.5,0.49]],[16,"chat_share",false,[-11,-12,-13],[[4,1,0,false,-9,[7],8],[2,1,10,20,15,15,-10,[5,127,93]]],[0,"c9n7Y+kg9Amq00DOy4HyFx",1],[5,127,93],[0,1,1],[214,20,0,0,0,0,1,1,1,1]],[17,"chat_share",[-16,-17,-18],[[4,1,0,false,-14,[18],19],[2,1,20,10,15,15,-15,[5,127,93]]],[0,"0b4D7OPTpCh4aBiUIY8DDo",1],[5,127,93],[0,0,1],[-214,20,0,0,0,0,1,1,1,1]],[18,"chat_player_own",false,1,[-20,-21,2,-22],[-19],[0,"f9nswduFNDz4yGt+8Lb4pc",1]],[19,"chat_player_others",1,[-24,-25,3,-26],[-23],[0,"9fufrVM4RMwrfq7bJteFJx",1]],[6,"chat_tx",false,4,[-29],[[4,1,0,false,-27,[1],2],[2,1,10,20,15,15,-28,[5,30,45.28]]],[0,"e7lF6ozOREsrZg1wu+xMy3",1],[5,30,45.28],[0,1,1],[214,20,0,0,0,0,1,1,1,1]],[6,"chat_tx",false,5,[-32],[[4,1,0,false,-30,[12],13],[2,1,20,10,15,15,-31,[5,30,45.28]]],[0,"0f95A6X3NFQIihWZJ4tW0k",1],[5,30,45.28],[0,0,1],[-214,20,0,0,0,0,1,1,1,1]],[21,"chat_bg_system",false,1,[-36],[[[26,1,0,-33,[23]],-34,[2,1,6,6,4,4,-35,[5,392,34]]],4,1,4],[0,"7d8FsKuEJAXKrF4V3qRK2I",1],[5,392,34]],[7,"node_name",4,[-38,-39],[[27,1,1,10,1,-37,[5,14,30]]],[0,"dchqqB2kFAXZmtpB3cZgsV",1],[5,14,30],[0,1,0.5],[205,40,0,0,0,0,1,1,1,1]],[7,"node_name",5,[-41,-42],[[28,1,1,10,-40,[5,14,30]]],[0,"cdsoe2LmNKgYH5rtbb4SLn",1],[5,14,30],[0,0,0.5],[-205,40,0,0,0,0,1,1,1,1]],[3,"node_check",2,[[5,2,false,-43,[3],4]],[0,"93Q/sSG5tFIbwJLplG1y82",1],[5,97,26],[0,1,0.5],[-20,-65,0,0,0,0,1,1,1,1]],[3,"node_join",2,[[5,2,false,-44,[5],6]],[0,"62ZDj7oQBKvaMYJ0uITtVJ",1],[5,97,26],[0,1,0.5],[-20,-65,0,0,0,0,1,1,1,1]],[22,"chat_view_server",9,[[-45,[9,2,-46,[4,4279585029]]],1,4],[0,"6fd0wJz9NFno9pEbcMAcyR",1],[4,4282504849],[5,4,39.28],[0,1,0.5]],[3,"node_check",3,[[5,2,false,-47,[14],15]],[0,"5caZBNKnRLt58toi9xEAY+",1],[5,97,26],[0,0,0.5],[20,-65,0,0,0,0,1,1,1,1]],[3,"node_join",3,[[5,2,false,-48,[16],17]],[0,"fa/S5AyXRBf7G/6MQoxOC0",1],[5,97,26],[0,0,0.5],[20,-65,0,0,0,0,1,1,1,1]],[23,"chat_view_server",10,[[-49,[9,2,-50,[4,4279585029]]],1,4],[0,"05XkaueOtAX5kBbuoCfhCO",1],[4,4282504849],[5,4,39.28],[0,1,0.5],[4,0,0,0,0,0,1,1,1,1]],[8,"head_item",4,[0,"49ShPpmlNCBoF3FQ6VZJAY",1],[5,112,112],[280,0,0,0,0,0,1,1,1,1]],[1,"tx",6,[-51],[0,"6d09qn/bFDCL1EffLwu5Or",1],[4,4279389047],[5,0,35.28],[0,1,1],[-20,-15,0,0,0,0,1,1,1,1]],[10,24,28,1,18,[0]],[1,"tx",2,[-52],[0,"05Ws74/39F4pW1RpwZj5e4",1],[4,4278855515],[5,0,35.28],[0,1,1],[-20,-15,0,0,0,0,1,1,1,1]],[30,"",2,24,28,false,20],[11,26,28,1,1,1,13,[9]],[1,"chat_view_name",9,[-53],[0,"9dit5/6ahHZqdDIS7KkZRi",1],[4,4278855515],[5,0,35.28],[0,1,0.5],[-14,0,0,0,0,0,1,1,1,1]],[12,26,28,1,1,23,[10]],[13,4,17,22,24,6,19,2,21,11,12],[8,"head_item",5,[0,"6fOc6z01hOkI7NrY8k7ylW",1],[5,112,112],[-280,0,0,0,0,0,1,1,1,1]],[1,"tx",7,[-54],[0,"16r1Y4yAdHCrVq0783dZDj",1],[4,4279389047],[5,0,35.28],[0,0,1],[20,-15,0,0,0,0,1,1,1,1]],[10,24,28,1,27,[11]],[1,"tx",3,[-55],[0,"d9f830lllB1oyBuugjCzmk",1],[4,4279389047],[5,0,35.28],[0,0,1],[20,-15,0,0,0,0,1,1,1,1]],[31,"",24,28,false,29],[11,26,28,1,1,1,16,[20]],[1,"chat_view_name",10,[-56],[0,"c8+1QLwphAr4kr4yQV6imO",1],[4,4278855515],[5,0,35.28],[0,1,0.5],[14,0,0,0,0,0,1,1,1,1]],[12,26,28,1,1,32,[21]],[13,5,26,31,33,7,28,3,30,14,15],[20,"tx",8,[-57],[0,"6ci9saPChE7qVGwa2Ip2GV",1],[5,380,26]],[29,"系统消息：一雷杀三个队友，畏罪潜逃了！",20,26,1,1,2,35,[22]],[32,8,36]],0,[0,5,1,0,6,37,0,7,34,0,8,25,0,0,1,0,-1,4,0,-2,5,0,-3,8,0,0,2,0,0,2,0,-1,20,0,-2,11,0,-3,12,0,0,3,0,0,3,0,-1,29,0,-2,14,0,-3,15,0,-1,25,0,-1,17,0,-2,6,0,-4,9,0,-1,34,0,-1,26,0,-2,7,0,-4,10,0,0,6,0,0,6,0,-1,18,0,0,7,0,0,7,0,-1,27,0,0,8,0,-2,37,0,0,8,0,-1,35,0,0,9,0,-1,13,0,-2,23,0,0,10,0,-1,16,0,-2,32,0,0,11,0,0,12,0,-1,22,0,0,13,0,0,14,0,0,15,0,-1,31,0,0,16,0,-1,19,0,-1,21,0,-1,24,0,-1,28,0,-1,30,0,-1,33,0,-1,36,0,9,1,2,3,4,3,3,5,57],[0,0,0,0,0,0,0,0,0,0,0,0,0,0,0,0,0,0,0,0,0,0,0,0,25,34],[-1,-1,1,-1,1,-1,1,-1,1,-1,-1,-1,-1,1,-1,1,-1,1,-1,1,-1,-1,-1,-1,4,4],[0,0,1,0,2,0,3,0,1,0,0,0,0,4,0,2,0,3,0,4,0,0,0,0,5,5]],[[{"name":"frame_dhk","rect":[0,0,34,57],"offset":[0,0],"originalSize":[34,57],"capInsets":[16,8,8,8]}],[1],0,[0],[2],[9]]]]