[1,["738955c0-6cd3-40d7-bcf4-a349fb5874b6","18a943d3-0de4-43fb-b649-18d76df87e11@6c48a"],["node","root","data","_skeletonData"],[["cc.Prefab",["_name"],2],["cc.Node",["_name","_components","_prefab"],2,9,4],["cc.UITransform",["node","__prefab","_contentSize","_anchorPoint"],3,1,4,5,5],["cc.CompPrefabInfo",["fileId"],2],["sp.Skeleton",["defaultSkin","defaultAnimation","_preCacheMode","node","__prefab","_skeletonData"],0,1,4,6],["cc.PrefabInfo",["fileId","instance","targetOverrides","nestedPrefabInstanceRoots","root","asset"],-1,1,1],["sp.SkeletonData",["_name","_atlasText","textureNames","_skeletonJson","textures"],-1,3]],[[3,0,2],[0,0,2],[1,0,1,2,2],[2,0,1,2,3,1],[4,0,1,2,3,4,5,4],[5,0,1,2,3,4,5,5],[6,0,1,2,3,4,5]],[[[[1,"back1"],[2,"back1",[[3,-2,[0,"d9TddzPNlL/ZMjpWnuL17V"],[5,459.260009765625,193.44000244140625],[0,0.49843225796848595,0.16640817938605776]],[4,"default","idle",0,-3,[0,"50yfNNnXNNmr1gn4aFQ2wh"],0]],[5,"24YdbuY7JC0pbuLpuANsNr",null,null,null,-1,0]]],0,[0,1,1,0,0,1,0,0,1,0,2,1,3],[0],[3],[0]],[[[6,"bs_cb1","\nbs_cb1.png\nsize: 284,284\nformat: RGBA8888\nfilter: Linear,Linear\nrepeat: none\nchibang1\n  rotate: false\n  xy: 2, 87\n  size: 223, 193\n  orig: 223, 193\n  offset: 0, 0\n  index: -1\nchibang2\n  rotate: false\n  xy: 227, 205\n  size: 53, 75\n  orig: 55, 77\n  offset: 1, 1\n  index: -1\n",["bs_cb1.png"],{"skeleton":{"hash":"nqyyHCrYSEFUFMHxGwcv6xP/uto","spine":"3.8.99","x":-228.91,"y":-32.19,"width":459.26,"height":193.44},"bones":[{"name":"root","scaleX":0.52,"scaleY":0.52},{"name":"cb1","parent":"root"},{"name":"bone","parent":"cb1","x":1.38,"y":39.16},{"name":"chibang1","parent":"bone","length":79.43,"rotation":28.27,"x":28.29,"y":2.59},{"name":"chibang2","parent":"chibang1","length":97.21,"rotation":57.91,"x":79.43},{"name":"chibang3","parent":"chibang2","length":116.53,"rotation":-61.43,"x":97.21},{"name":"chibang4","parent":"chibang3","length":99.16,"rotation":-29.86,"x":116.53},{"name":"chibang5","parent":"chibang4","length":66.01,"rotation":13.81,"x":99.16},{"name":"chibang6","parent":"chibang5","length":66.78,"rotation":18.53,"x":66.01},{"name":"chibang7","parent":"chibang2","length":119.91,"rotation":-105.07,"x":91.66,"y":-13.92},{"name":"chibang8","parent":"chibang7","length":67.49,"rotation":-18.69,"x":119.91},{"name":"chibang9","parent":"chibang8","length":59.68,"rotation":-18.27,"x":67.96,"y":0.36},{"name":"chibang10","parent":"chibang2","length":96.09,"rotation":-144.44,"x":82.94,"y":-6.84},{"name":"chibang11","parent":"chibang10","length":65.72,"rotation":-10.23,"x":96.09},{"name":"chibang12","parent":"chibang11","length":63.08,"rotation":-17.24,"x":65.72},{"name":"bone2","parent":"cb1","x":1.38,"y":39.16,"scaleX":-1},{"name":"chibang13","parent":"bone2","length":79.43,"rotation":28.27,"x":28.29,"y":2.59},{"name":"chibang14","parent":"chibang13","length":97.21,"rotation":57.91,"x":79.43},{"name":"chibang15","parent":"chibang14","length":116.53,"rotation":-61.43,"x":97.21},{"name":"chibang16","parent":"chibang15","length":99.16,"rotation":-29.86,"x":116.53},{"name":"chibang17","parent":"chibang16","length":66.01,"rotation":13.81,"x":99.16},{"name":"chibang18","parent":"chibang17","length":66.78,"rotation":18.53,"x":66.01},{"name":"chibang19","parent":"chibang14","length":119.91,"rotation":-105.07,"x":91.66,"y":-13.92},{"name":"chibang20","parent":"chibang19","length":67.49,"rotation":-18.69,"x":119.91},{"name":"chibang21","parent":"chibang20","length":59.68,"rotation":-18.27,"x":67.96,"y":0.36},{"name":"chibang22","parent":"chibang14","length":96.09,"rotation":-144.44,"x":82.94,"y":-6.84},{"name":"chibang23","parent":"chibang22","length":65.72,"rotation":-10.23,"x":96.09},{"name":"chibang24","parent":"chibang23","length":63.08,"rotation":-17.24,"x":65.72}],"slots":[{"name":"chibang1","bone":"chibang1","attachment":"chibang1"},{"name":"chibang3","bone":"chibang13","attachment":"chibang1"},{"name":"chibang2","bone":"chibang2","attachment":"chibang2"},{"name":"chibang4","bone":"chibang14","attachment":"chibang2"}],"skins":[{"name":"default","attachments":{"chibang1":{"chibang1":{"type":"mesh","hull":34,"uvs":[0,0.61113,0.0883,0.57636,0.15149,0.58901,0.17621,0.31719,0.21192,0.29823,0.3273,0.30297,0.38636,0.26979,0.3534,0.24134,0.3218,0.13546,0.30807,0,0.37812,0.09437,0.50586,0.17971,0.60201,0.20341,0.64733,0.15916,0.77507,0.19551,0.90144,0.16074,1,0.10069,0.9399,0.20499,0.81765,0.3251,0.70502,0.43888,0.70777,0.64274,0.74348,0.80709,0.64733,0.66328,0.47701,0.64748,0.43993,0.83079,0.40256,1,0.37646,0.86128,0.29268,0.80755,0.20889,0.87234,0.1567,0.94504,0.16906,0.82651,0.11549,0.7712,0.06879,0.81071,0,0.76014,0.47255,0.32787,0.59068,0.38476,0.31597,0.47642,0.41212,0.5507,0.27751,0.66132,0.49474,0.27601,0.59993,0.29706,0.66579,0.33074,0.80758,0.28128,0.6591,0.57309,0.53835,0.46469,0.51274,0.55309,0.42401,0.51099,0.38011,0.58887,0.42859,0.71622,0.35746,0.76134,0.30715,0.64347,0.24038,0.50981,0.38364,0.39511],"triangles":[26,49,24,25,26,24,51,4,36,47,36,37,50,51,36,50,36,47,50,38,51,47,37,23,48,47,23,50,47,48,49,50,48,38,50,49,27,38,49,24,48,23,49,48,24,27,49,26,43,19,20,22,45,43,22,43,20,22,20,21,44,34,35,45,46,44,19,44,35,43,44,19,45,44,43,23,45,22,23,37,45,17,15,16,42,15,17,36,5,52,52,34,44,46,52,44,37,46,45,36,52,46,37,36,46,8,9,10,7,8,10,6,7,10,11,6,10,34,6,39,52,5,6,52,6,34,36,4,5,3,4,51,38,2,51,51,2,3,42,14,15,18,42,17,41,14,42,41,42,18,19,41,18,39,6,11,39,11,12,40,39,12,12,13,41,40,12,41,35,39,40,35,40,41,34,39,35,41,13,14,35,41,19,31,33,0,31,1,2,31,2,38,31,0,1,30,31,38,32,33,31,27,30,38,28,30,27,29,30,28],"vertices":[1,3,6.46,43.09,1,2,3,45.87,36.58,0.98085,4,13.16,47.87,0.01915,2,3,67.46,19.63,0.58422,4,10.27,20.57,0.41578,2,4,111.86,16.74,0.31297,5,-7.69,20.87,0.68703,2,4,119.92,1.96,0.05676,5,9.14,20.88,0.94324,2,5,53.24,-1.4,0.98182,9,24.62,37.47,0.01818,3,6,-30.1,-18.18,0.00005,5,81.37,-0.78,0.9834,9,44.54,57.33,0.01655,1,5,72.99,14.74,1,1,5,77.2,56.17,1,1,5,92.96,104.39,1,2,6,-39.42,46.51,0.01372,5,105.49,59.96,0.98628,2,6,17.86,19.75,0.96184,5,141.85,8.24,0.03816,2,6,59.63,14.62,0.9993,7,-34.89,23.64,0.0007,2,6,77.49,32.75,0.87487,7,-13.22,36.97,0.12513,1,7,38.77,15.33,1,1,8,33.05,9.93,1,1,8,80.78,10.49,1,1,8,40.15,-12.24,1,4,6,155.59,-22.25,0.00161,7,49.49,-35.08,0.96196,8,-26.82,-28.01,0.00538,10,69.09,126.4,0.03105,5,6,111.34,-68.7,0.20508,7,-4.57,-69.62,0.25519,9,193.95,41.94,0.00047,10,56.69,63.45,0.51151,11,-30.48,56.38,0.02775,4,6,119.25,-144.13,0.00023,7,-14.89,-144.76,0.00042,10,103.86,4.06,0.00022,11,32.93,14.77,0.99913,1,11,92.1,-6.91,1,3,10,88.02,-17.77,0.03106,11,24.73,-10.92,0.96728,13,62.93,114.37,0.00167,5,9,126.72,-63.06,0.08178,10,26.65,-57.55,0.36485,11,-21.07,-67.94,0.00203,13,30.73,48.71,0.52745,12,134.98,42.47,0.02389,2,13,88.35,8.93,0.00234,14,18.97,15.23,0.99766,1,14,80.54,-5.41,1,3,3,104.29,-115.18,0.00923,13,88.94,-20.5,0.01879,14,28.25,-12.7,0.97198,4,3,82.17,-80.6,0.35148,4,-66.83,-45.13,0.00221,13,57.19,-46.53,0.50115,14,5.65,-46.97,0.14515,3,3,39.17,-84.84,0.70702,13,66.46,-88.73,0.28701,14,27.01,-84.53,0.00597,2,3,6.69,-98.07,0.72606,13,83.43,-119.43,0.27394,3,3,32.23,-61.75,0.7476,13,44.35,-98.34,0.24855,14,8.74,-100.26,0.00385,3,3,21.79,-32.77,0.93355,13,16.8,-112.12,0.06643,14,-13.49,-121.59,0.00002,2,3,-2.78,-36.24,0.99155,13,23.14,-136.11,0.00845,1,3,-19.8,-5.73,1,4,6,8.56,-36.42,0.32224,5,105.82,-35.85,0.30849,9,86.44,48.82,0.35007,10,-47.35,35.52,0.0192,5,6,60.8,-53,0.42939,7,-49.9,-42.32,0.03949,5,142.87,-76.24,0.00516,9,141.13,45.15,0.12063,10,5.63,49.57,0.40533,2,9,40.91,-25.15,0.36312,12,44.6,17.34,0.63688,4,9,88.79,-37.98,0.4079,10,-17.31,-45.95,0.09466,13,-12.95,36.07,0.19348,12,89.75,37.8,0.30396,5,3,102.22,-29.61,0.23286,4,-12.98,-35.04,0.16989,13,4.2,-32.62,0.37358,12,94.43,-32.85,0.22312,14,-49.09,-49.39,0.00056,4,6,16.31,-16.36,0.71704,5,122.52,-22.3,0.1732,9,89.18,70.15,0.09785,10,-51.59,56.6,0.01191,5,6,61.85,-20.15,0.85815,7,-41.04,-10.67,0.00809,5,160.13,-48.27,0.00152,9,134.32,77.31,0.04089,10,-11.13,77.85,0.09135,4,6,91.04,-30.13,0.54662,7,-15.07,-27.32,0.25438,9,165.04,74.57,0.01119,10,18.86,85.1,0.18781,3,7,47.69,-18.31,0.98303,8,-23.19,-11.54,0.00456,10,55.74,136.69,0.01241,4,6,96.2,-120.18,0.01168,7,-31.55,-116,0.00989,10,71.55,11.9,0.43684,11,-0.21,12.09,0.54159,5,6,41.14,-84.61,0.06347,7,-76.53,-68.31,0.0038,5,110.09,-93.86,0.00265,9,129.56,9.78,0.20918,10,6,12.35,0.7209,4,9,129.83,-24.89,0.13073,10,17.37,-20.4,0.75356,13,3.67,75.81,0.1001,12,113.17,73.95,0.01562,4,9,88.82,-22.36,0.69407,10,-22.28,-31.14,0.05983,13,-24.83,46.22,0.07415,12,79.87,49.9,0.17195,4,9,80.42,-55.85,0.14076,10,-19.51,-65.56,0.04465,13,-4.77,18.12,0.33908,12,94.62,18.67,0.47551,4,9,115.38,-93.96,0.0093,10,25.82,-90.46,0.04531,13,46.92,20.04,0.94273,14,-23.9,13.57,0.00266,4,3,114.74,-78.59,0.06005,4,-47.83,-71.66,0.00121,13,51.37,-14.43,0.83998,14,-9.43,-18.04,0.09877,4,3,116.54,-29.77,0.08354,4,-5.51,-47.25,0.0979,13,2.68,-18.38,0.46608,12,95.46,-18.57,0.35248,2,4,42.2,-15.43,0.50817,12,38.14,-16.71,0.49183,3,6,-27.12,-64.72,0.0053,5,60.79,-42.63,0.14604,9,58.53,12.84,0.84866]}},"chibang2":{"chibang2":{"x":117.22,"y":-1.76,"rotation":-86.19,"width":105,"height":148}},"chibang3":{"chibang1":{"type":"mesh","hull":34,"uvs":[0,0.61113,0.0883,0.57636,0.15149,0.58901,0.17621,0.31719,0.21192,0.29823,0.3273,0.30297,0.38636,0.26979,0.3534,0.24134,0.3218,0.13546,0.30807,0,0.37812,0.09437,0.50586,0.17971,0.60201,0.20341,0.64733,0.15916,0.77507,0.19551,0.90144,0.16074,1,0.10069,0.9399,0.20499,0.81765,0.3251,0.70502,0.43888,0.70777,0.64274,0.74348,0.80709,0.64733,0.66328,0.47701,0.64748,0.43993,0.83079,0.40256,1,0.37646,0.86128,0.29268,0.80755,0.20889,0.87234,0.1567,0.94504,0.16906,0.82651,0.11549,0.7712,0.06879,0.81071,0,0.76014,0.47255,0.32787,0.59068,0.38476,0.31597,0.47642,0.41212,0.5507,0.27751,0.66132,0.49474,0.27601,0.59993,0.29706,0.66579,0.33074,0.80758,0.28128,0.6591,0.57309,0.53835,0.46469,0.51274,0.55309,0.42401,0.51099,0.38011,0.58887,0.42859,0.71622,0.35746,0.76134,0.30715,0.64347,0.24038,0.50981,0.38364,0.39511],"triangles":[26,49,24,25,26,24,51,4,36,47,36,37,50,51,36,50,36,47,50,38,51,47,37,23,48,47,23,50,47,48,49,50,48,38,50,49,27,38,49,24,48,23,49,48,24,27,49,26,43,19,20,22,45,43,22,43,20,22,20,21,44,34,35,45,46,44,19,44,35,43,44,19,45,44,43,23,45,22,23,37,45,17,15,16,42,15,17,36,5,52,52,34,44,46,52,44,37,46,45,36,52,46,37,36,46,8,9,10,7,8,10,6,7,10,11,6,10,34,6,39,52,5,6,52,6,34,36,4,5,3,4,51,38,2,51,51,2,3,42,14,15,18,42,17,41,14,42,41,42,18,19,41,18,39,6,11,39,11,12,40,39,12,12,13,41,40,12,41,35,39,40,35,40,41,34,39,35,41,13,14,35,41,19,31,33,0,31,1,2,31,2,38,31,0,1,30,31,38,32,33,31,27,30,38,28,30,27,29,30,28],"vertices":[1,16,6.46,43.09,1,2,16,45.87,36.58,0.98085,17,13.16,47.87,0.01915,2,16,67.46,19.63,0.58422,17,10.27,20.57,0.41578,2,17,111.86,16.74,0.31297,18,-7.69,20.87,0.68703,2,17,119.92,1.96,0.05676,18,9.14,20.88,0.94324,2,18,53.24,-1.4,0.98182,22,24.62,37.47,0.01818,3,19,-30.1,-18.18,0.00005,18,81.37,-0.78,0.9834,22,44.54,57.33,0.01655,1,18,72.99,14.74,1,1,18,77.2,56.17,1,1,18,92.96,104.39,1,2,19,-39.42,46.51,0.01372,18,105.49,59.96,0.98628,2,19,17.86,19.75,0.96184,18,141.85,8.24,0.03816,2,19,59.63,14.62,0.9993,20,-34.89,23.64,0.0007,2,19,77.49,32.75,0.87487,20,-13.22,36.97,0.12513,1,20,38.77,15.33,1,1,21,33.05,9.93,1,1,21,80.78,10.49,1,1,21,40.15,-12.24,1,4,19,155.59,-22.25,0.00161,20,49.49,-35.08,0.96196,21,-26.82,-28.01,0.00538,23,69.09,126.4,0.03105,5,19,111.34,-68.7,0.20508,20,-4.57,-69.62,0.25519,22,193.95,41.94,0.00047,23,56.69,63.45,0.51151,24,-30.48,56.38,0.02775,4,19,119.25,-144.13,0.00023,20,-14.89,-144.76,0.00042,23,103.86,4.06,0.00022,24,32.93,14.77,0.99913,1,24,92.1,-6.91,1,3,23,88.02,-17.77,0.03106,24,24.73,-10.92,0.96728,26,62.93,114.37,0.00167,5,22,126.72,-63.06,0.08178,23,26.65,-57.55,0.36485,24,-21.07,-67.94,0.00203,26,30.73,48.71,0.52745,25,134.98,42.47,0.02389,2,26,88.35,8.93,0.00234,27,18.97,15.23,0.99766,1,27,80.54,-5.41,1,3,16,104.29,-115.18,0.00923,26,88.94,-20.5,0.01879,27,28.25,-12.7,0.97198,4,16,82.17,-80.6,0.35148,17,-66.83,-45.13,0.00221,26,57.19,-46.53,0.50115,27,5.65,-46.97,0.14515,3,16,39.17,-84.84,0.70702,26,66.46,-88.73,0.28701,27,27.01,-84.53,0.00597,2,16,6.69,-98.07,0.72606,26,83.43,-119.43,0.27394,3,16,32.23,-61.75,0.7476,26,44.35,-98.34,0.24855,27,8.74,-100.26,0.00385,3,16,21.79,-32.77,0.93355,26,16.8,-112.12,0.06643,27,-13.49,-121.59,0.00002,2,16,-2.78,-36.24,0.99155,26,23.14,-136.11,0.00845,1,16,-19.8,-5.73,1,4,19,8.56,-36.42,0.32224,18,105.82,-35.85,0.30849,22,86.44,48.82,0.35007,23,-47.35,35.52,0.0192,5,19,60.8,-53,0.42939,20,-49.9,-42.32,0.03949,18,142.87,-76.24,0.00516,22,141.13,45.15,0.12063,23,5.63,49.57,0.40533,2,22,40.91,-25.15,0.36312,25,44.6,17.34,0.63688,4,22,88.79,-37.98,0.4079,23,-17.31,-45.95,0.09466,26,-12.95,36.07,0.19348,25,89.75,37.8,0.30396,5,16,102.22,-29.61,0.23286,17,-12.98,-35.04,0.16989,26,4.2,-32.62,0.37358,25,94.43,-32.85,0.22312,27,-49.09,-49.39,0.00056,4,19,16.31,-16.36,0.71704,18,122.52,-22.3,0.1732,22,89.18,70.15,0.09785,23,-51.59,56.6,0.01191,5,19,61.85,-20.15,0.85815,20,-41.04,-10.67,0.00809,18,160.13,-48.27,0.00152,22,134.32,77.31,0.04089,23,-11.13,77.85,0.09135,4,19,91.04,-30.13,0.54662,20,-15.07,-27.32,0.25438,22,165.04,74.57,0.01119,23,18.86,85.1,0.18781,3,20,47.69,-18.31,0.98303,21,-23.19,-11.54,0.00456,23,55.74,136.69,0.01241,4,19,96.2,-120.18,0.01168,20,-31.55,-116,0.00989,23,71.55,11.9,0.43684,24,-0.21,12.09,0.54159,5,19,41.14,-84.61,0.06347,20,-76.53,-68.31,0.0038,18,110.09,-93.86,0.00265,22,129.56,9.78,0.20918,23,6,12.35,0.7209,4,22,129.83,-24.89,0.13073,23,17.37,-20.4,0.75356,26,3.67,75.81,0.1001,25,113.17,73.95,0.01562,4,22,88.82,-22.36,0.69407,23,-22.28,-31.14,0.05983,26,-24.83,46.22,0.07415,25,79.87,49.9,0.17195,4,22,80.42,-55.85,0.14076,23,-19.51,-65.56,0.04465,26,-4.77,18.12,0.33908,25,94.62,18.67,0.47551,4,22,115.38,-93.96,0.0093,23,25.82,-90.46,0.04531,26,46.92,20.04,0.94273,27,-23.9,13.57,0.00266,4,16,114.74,-78.59,0.06005,17,-47.83,-71.66,0.00121,26,51.37,-14.43,0.83998,27,-9.43,-18.04,0.09877,4,16,116.54,-29.77,0.08354,17,-5.51,-47.25,0.0979,26,2.68,-18.38,0.46608,25,95.46,-18.57,0.35248,2,17,42.2,-15.43,0.50817,25,38.14,-16.71,0.49183,3,19,-27.12,-64.72,0.0053,18,60.79,-42.63,0.14604,22,58.53,12.84,0.84866]}},"chibang4":{"chibang2":{"x":117.22,"y":-1.76,"rotation":-86.19,"width":105,"height":148}}}}],"animations":{"idle":{"bones":{"chibang1":{"rotate":[{"angle":7.18,"curve":0.25,"c3":0.75},{"time":1,"angle":-12.24,"curve":0.25,"c3":0.75},{"time":2,"angle":7.18}]},"chibang6":{"rotate":[{"angle":-18.57,"curve":0.379,"c2":0.6,"c3":0.724},{"time":0.2333,"angle":-24.96,"curve":0.25,"c3":0.75},{"time":1.2333,"angle":9.69,"curve":0.242,"c3":0.667,"c4":0.67},{"time":2,"angle":-18.57}]},"chibang5":{"rotate":[{"angle":-30.58,"curve":0.25,"c3":0.75},{"time":1,"angle":9.26,"curve":0.25,"c3":0.75},{"time":2,"angle":-30.58}]},"chibang4":{"rotate":[{"angle":-19.66,"curve":0.333,"c2":0.33,"c3":0.758},{"time":0.7333,"angle":9,"curve":0.25,"c3":0.75},{"time":1.7333,"angle":-26.14,"curve":0.276,"c3":0.621,"c4":0.4},{"time":2,"angle":-19.66}]},"chibang3":{"rotate":[{"angle":-5.49,"curve":0.375,"c2":0.5,"c3":0.75},{"time":0.5,"angle":9.13,"curve":0.25,"c3":0.75},{"time":1.5,"angle":-20.1,"curve":0.25,"c3":0.625,"c4":0.5},{"time":2,"angle":-5.49}]},"chibang2":{"rotate":[{"angle":7.14,"curve":0.379,"c2":0.6,"c3":0.724},{"time":0.2333,"angle":10.92,"curve":0.25,"c3":0.75},{"time":1.2333,"angle":-9.56,"curve":0.242,"c3":0.667,"c4":0.67},{"time":2,"angle":7.14}]},"chibang7":{"rotate":[{"angle":-0.92,"curve":0.339,"c2":0.35,"c3":0.687,"c4":0.73},{"time":0.3,"angle":9.84,"curve":0.379,"c2":0.6,"c3":0.724},{"time":0.5667,"angle":14.87,"curve":0.25,"c3":0.75},{"time":1.5667,"angle":-12.38,"curve":0.254,"c3":0.62,"c4":0.47},{"time":2,"angle":-0.92}]},"chibang8":{"rotate":[{"angle":-13.51,"curve":0.303,"c2":0.23,"c3":0.652,"c4":0.62},{"time":0.3,"angle":-4.33,"curve":0.375,"c2":0.5,"c3":0.75},{"time":0.8,"angle":7.63,"curve":0.25,"c3":0.75},{"time":1.8,"angle":-16.28,"curve":0.286,"c3":0.626,"c4":0.38},{"time":2,"angle":-13.51}]},"chibang9":{"rotate":[{"angle":-13.9,"curve":0.351,"c2":0.65,"c3":0.686},{"time":0.0667,"angle":-14.48,"curve":0.276,"c3":0.621,"c4":0.4},{"time":0.3,"angle":-9.44,"curve":0.333,"c2":0.33,"c3":0.758},{"time":1.0667,"angle":12.85,"curve":0.247,"c3":0.724,"c4":0.89},{"time":2,"angle":-13.9}]},"chibang10":{"rotate":[{"angle":18.65,"curve":0.379,"c2":0.6,"c3":0.724},{"time":0.2333,"angle":24.84,"curve":0.25,"c3":0.75},{"time":1.2333,"angle":-8.7,"curve":0.242,"c3":0.667,"c4":0.67},{"time":2,"angle":18.65}]},"chibang11":{"rotate":[{"angle":-1.4,"curve":0.375,"c2":0.5,"c3":0.75},{"time":0.5,"angle":4.88,"curve":0.25,"c3":0.75},{"time":1.5,"angle":-7.67,"curve":0.25,"c3":0.625,"c4":0.5},{"time":2,"angle":-1.4}]},"chibang12":{"rotate":[{"angle":-3.57,"curve":0.333,"c2":0.33,"c3":0.758},{"time":0.7333,"angle":3.31,"curve":0.25,"c3":0.75},{"time":1.7333,"angle":-5.13,"curve":0.276,"c3":0.621,"c4":0.4},{"time":2,"angle":-3.57}]},"chibang18":{"rotate":[{"angle":-18.57,"curve":0.379,"c2":0.6,"c3":0.724},{"time":0.2333,"angle":-24.96,"curve":0.25,"c3":0.75},{"time":1.2333,"angle":9.69,"curve":0.242,"c3":0.667,"c4":0.67},{"time":2,"angle":-18.57}]},"chibang17":{"rotate":[{"angle":-30.58,"curve":0.25,"c3":0.75},{"time":1,"angle":9.26,"curve":0.25,"c3":0.75},{"time":2,"angle":-30.58}]},"chibang16":{"rotate":[{"angle":-19.66,"curve":0.333,"c2":0.33,"c3":0.758},{"time":0.7333,"angle":9,"curve":0.25,"c3":0.75},{"time":1.7333,"angle":-26.14,"curve":0.276,"c3":0.621,"c4":0.4},{"time":2,"angle":-19.66}]},"chibang15":{"rotate":[{"angle":-5.49,"curve":0.375,"c2":0.5,"c3":0.75},{"time":0.5,"angle":9.13,"curve":0.25,"c3":0.75},{"time":1.5,"angle":-20.1,"curve":0.25,"c3":0.625,"c4":0.5},{"time":2,"angle":-5.49}]},"chibang21":{"rotate":[{"angle":-9.44,"curve":0.333,"c2":0.33,"c3":0.758},{"time":0.7333,"angle":12.85,"curve":0.25,"c3":0.75},{"time":1.7333,"angle":-14.48,"curve":0.276,"c3":0.621,"c4":0.4},{"time":2,"angle":-9.44}]},"chibang20":{"rotate":[{"angle":-4.33,"curve":0.375,"c2":0.5,"c3":0.75},{"time":0.5,"angle":7.63,"curve":0.25,"c3":0.75},{"time":1.5,"angle":-16.28,"curve":0.25,"c3":0.625,"c4":0.5},{"time":2,"angle":-4.33}]},"chibang19":{"rotate":[{"angle":9.84,"curve":0.379,"c2":0.6,"c3":0.724},{"time":0.2333,"angle":14.87,"curve":0.25,"c3":0.75},{"time":1.2333,"angle":-12.38,"curve":0.242,"c3":0.667,"c4":0.67},{"time":2,"angle":9.84}]},"chibang24":{"rotate":[{"angle":-3.57,"curve":0.333,"c2":0.33,"c3":0.758},{"time":0.7333,"angle":3.31,"curve":0.25,"c3":0.75},{"time":1.7333,"angle":-5.13,"curve":0.276,"c3":0.621,"c4":0.4},{"time":2,"angle":-3.57}]},"chibang23":{"rotate":[{"angle":-1.4,"curve":0.375,"c2":0.5,"c3":0.75},{"time":0.5,"angle":4.88,"curve":0.25,"c3":0.75},{"time":1.5,"angle":-7.67,"curve":0.25,"c3":0.625,"c4":0.5},{"time":2,"angle":-1.4}]},"chibang22":{"rotate":[{"angle":18.65,"curve":0.379,"c2":0.6,"c3":0.724},{"time":0.2333,"angle":24.84,"curve":0.25,"c3":0.75},{"time":1.2333,"angle":-8.7,"curve":0.242,"c3":0.667,"c4":0.67},{"time":2,"angle":18.65}]},"chibang14":{"rotate":[{"angle":7.14,"curve":0.379,"c2":0.6,"c3":0.724},{"time":0.2333,"angle":10.92,"curve":0.25,"c3":0.75},{"time":1.2333,"angle":-9.56,"curve":0.242,"c3":0.667,"c4":0.67},{"time":2,"angle":7.14}]},"chibang13":{"rotate":[{"angle":7.18,"curve":0.25,"c3":0.75},{"time":1,"angle":-12.24,"curve":0.25,"c3":0.75},{"time":2,"angle":7.18}]}}}}},[0]]],0,0,[0],[-1],[1]]]]
