[1,["19110bf33@6c48a"],["_textureSource"],["cc.SpriteFrame","cc.SpriteAtlas"],0,[[[{"name":"AutoAtlas","spriteFrames":["monster9_5","abd90436-03a1-4dcb-a35d-82ca44bd9425@f9941","monster9_6","8414adac-5df9-48f0-a6ca-9e18a1f02a75@f9941","monster9_11","84f58801-18b7-4229-9630-f5208a983a22@f9941","monster9_8","8d13b075-95ee-43de-917e-132373e79934@f9941","monster9_12","fc21f5b9-5765-4ba4-9761-d760d8504af2@f9941","monster9_7","81329fb4-a95e-4792-bba6-12fb06cb5e84@f9941","monster9_10","5994a9de-1d60-4f80-b26c-91bc8307cac5@f9941","monster9_13","7a286985-90b8-4ae5-a965-7f9e345cf3cf@f9941","monster9_4","e45b410d-0928-465a-be1e-2ec03814f1ce@f9941","monster9_9","8b6631a8-e5ba-4314-90cc-035837482fb5@f9941","monster9_1","7f28bd04-9b8b-4b83-b2ed-3ba31d023484@f9941","monster9_3","8cb5d76b-4eb1-4d93-889a-df23fa34dfa5@f9941","monster9_2","94809295-0b1d-476a-ab0a-4d97e14ee7aa@f9941"]}],[1],0,[],[],[]],[[{"name":"monster9_10","rect":{"x":3,"y":303,"width":98,"height":169},"offset":{"x":-1,"y":1.5},"originalSize":{"width":118,"height":182},"rotated":false,"capInsets":[0,0,0,0],"packable":true,"pixelsToUnit":100,"pivot":{"x":0.5,"y":0.5},"meshType":0}],[0],0,[0],[0],[0]],[[{"name":"monster9_13","rect":{"x":107,"y":303,"width":85,"height":169},"offset":{"x":5.5,"y":2.5},"originalSize":{"width":118,"height":182},"rotated":false,"capInsets":[0,0,0,0],"packable":true,"pixelsToUnit":100,"pivot":{"x":0.5,"y":0.5},"meshType":0}],[0],0,[0],[0],[0]],[[{"name":"monster9_1","rect":{"x":198,"y":350,"width":82,"height":168},"offset":{"x":9,"y":1},"originalSize":{"width":118,"height":182},"rotated":false,"capInsets":[0,0,0,0],"packable":true,"pixelsToUnit":100,"pivot":{"x":0.5,"y":0.5},"meshType":0}],[0],0,[0],[0],[0]],[[{"name":"monster9_7","rect":{"x":3,"y":197,"width":100,"height":169},"offset":{"x":-1,"y":1.5},"originalSize":{"width":118,"height":182},"rotated":true,"capInsets":[0,0,0,0],"packable":true,"pixelsToUnit":100,"pivot":{"x":0.5,"y":0.5},"meshType":0}],[0],0,[0],[0],[0]],[[{"name":"monster9_6","rect":{"x":180,"y":3,"width":95,"height":170},"offset":{"x":-0.5,"y":3},"originalSize":{"width":118,"height":182},"rotated":true,"capInsets":[0,0,0,0],"packable":true,"pixelsToUnit":100,"pivot":{"x":0.5,"y":0.5},"meshType":0}],[0],0,[0],[0],[0]],[[{"name":"monster9_11","rect":{"x":3,"y":98,"width":93,"height":170},"offset":{"x":0.5,"y":3},"originalSize":{"width":118,"height":182},"rotated":true,"capInsets":[0,0,0,0],"packable":true,"pixelsToUnit":100,"pivot":{"x":0.5,"y":0.5},"meshType":0}],[0],0,[0],[0],[0]],[[{"name":"monster9_9","rect":{"x":355,"y":176,"width":103,"height":168},"offset":{"x":-1.5,"y":1},"originalSize":{"width":118,"height":182},"rotated":false,"capInsets":[0,0,0,0],"packable":true,"pixelsToUnit":100,"pivot":{"x":0.5,"y":0.5},"meshType":0}],[0],0,[0],[0],[0]],[[{"name":"monster9_3","rect":{"x":286,"y":350,"width":82,"height":168},"offset":{"x":9,"y":1},"originalSize":{"width":118,"height":182},"rotated":false,"capInsets":[0,0,0,0],"packable":true,"pixelsToUnit":100,"pivot":{"x":0.5,"y":0.5},"meshType":0}],[0],0,[0],[0],[0]],[[{"name":"monster9_8","rect":{"x":356,"y":3,"width":104,"height":167},"offset":{"x":-2,"y":0.5},"originalSize":{"width":118,"height":182},"rotated":false,"capInsets":[0,0,0,0],"packable":true,"pixelsToUnit":100,"pivot":{"x":0.5,"y":0.5},"meshType":0}],[0],0,[0],[0],[0]],[[{"name":"monster9_2","rect":{"x":374,"y":350,"width":83,"height":167},"offset":{"x":9.5,"y":0.5},"originalSize":{"width":118,"height":182},"rotated":false,"capInsets":[0,0,0,0],"packable":true,"pixelsToUnit":100,"pivot":{"x":0.5,"y":0.5},"meshType":0}],[0],0,[0],[0],[0]],[[{"name":"monster9_5","rect":{"x":3,"y":3,"width":89,"height":171},"offset":{"x":1.5,"y":3.5},"originalSize":{"width":118,"height":182},"rotated":true,"capInsets":[0,0,0,0],"packable":true,"pixelsToUnit":100,"pivot":{"x":0.5,"y":0.5},"meshType":0}],[0],0,[0],[0],[0]],[[{"name":"monster9_4","rect":{"x":178,"y":198,"width":84,"height":169},"offset":{"x":5,"y":2.5},"originalSize":{"width":118,"height":182},"rotated":true,"capInsets":[0,0,0,0],"packable":true,"pixelsToUnit":100,"pivot":{"x":0.5,"y":0.5},"meshType":0}],[0],0,[0],[0],[0]],[[{"name":"monster9_12","rect":{"x":179,"y":104,"width":88,"height":170},"offset":{"x":2,"y":3},"originalSize":{"width":118,"height":182},"rotated":true,"capInsets":[0,0,0,0],"packable":true,"pixelsToUnit":100,"pivot":{"x":0.5,"y":0.5},"meshType":0}],[0],0,[0],[0],[0]]]]
