[1,["ecpdLyjvZBwrvm+cedCcQy","12GdTwtBNA2q0BQm3OFnVA","2eE+/TwetIBq7BDHGVJ02a","e6vl9AY+VFPLgQFqosP1TB","c1bo7c0i5KQ6CsVxUit3eW","6b0ZQrZ+hDVqWtpa6j2Qda","09GNMu0PVERpABgmhlS1gA","50NJNGqJlJx6H/yissOZQP","0bXOUYO11GeatBx9f2iTD/","f2UsZi9YtP9Z0mi1RcJ4/x","0dANu7nW5GGZRkCXAVOhtG","edL3AD7VBFaY6Y0uHqSzrX","bbncpCtThEvbU6hojgDSN8","b97IJIhdFOK5+1IWUumV0P","5bmzqeBq5EDZaleuSCl/tT","65kvOeAe1JMLMIAJXEZFJ4","c8Q++w0VZBi4tn4cy7Q5E4"],["node","_spriteFrame","_textureSetter","scrollView","itemTemplate","root","p_nodeRightServ","p_nodeLeftMenu","p_btnClose","p_bgNode","data","_normalMaterial"],[["cc.Node",["_name","_prefab","_contentSize","_components","_trs","_parent","_children","_anchorPoint"],2,4,5,9,7,1,2,5],"cc.SpriteFrame",["cc.Sprite",["_sizeMode","_isTrimmedMode","_type","node","_materials","_spriteFrame"],0,1,3,6],["cc.Node",["_name","_parent","_components","_prefab","_contentSize","_children","_trs"],2,1,12,4,5,2,7],["cc.PrefabInfo",["fileId","root"],2,1],["cc.Prefab",["_name"],2],["cc.Widget",["alignMode","_alignFlags","_originalWidth","_originalHeight","node"],-1,1],["d2de8TuR89BXJ4ks0Wq4F9q",["node","p_bgNode","p_btnClose","p_nodeLeftMenu","p_nodeRightServ"],3,1,1,1,1,1],["ea961UF1PFDuI10cwhz2KU5",["spawnCount","totalCount","spacing","bufferZone","node","scrollView","itemTemplate"],-1,1,1,6],["cc.Layout",["_resize","_N$layoutType","_N$spacingX","node","_layoutSize"],0,1,5],["cc.Mask",["_N$alphaThreshold","node","_materials"],2,1,3],["cc.Button",["zoomScale","_N$transition","node"],1,1],["cc.ScrollView",["horizontal","brake","bounceDuration","_N$horizontalScrollBar","_N$verticalScrollBar","node","_N$content"],-2,1,1]],[[4,0,1,2],[0,0,5,3,1,2,4,2],[0,0,5,6,3,1,2,4,2],[2,3,4,5,1],[2,2,0,3,4,5,3],[2,1,3,4,5,2],[9,0,1,2,3,4,4],[0,0,5,6,3,1,2,2],[0,0,5,1,2,7,4,2],[8,0,1,2,3,4,5,6,5],[10,0,1,2,2],[12,0,1,2,3,4,5,6,6],[5,0,2],[0,0,6,3,1,2,4,2],[3,0,1,5,2,3,4,6,2],[3,0,1,5,2,3,4,2],[3,0,1,2,3,4,6,2],[6,0,1,2,3,4,5],[7,0,1,2,3,4,1],[4,1,1],[2,0,1,3,4,5,3],[11,0,1,2,3]],[[[{"name":"txt_title_qhfwq01_lang","rect":[0,0,148,28],"offset":[0,0],"originalSize":[148,28],"capInsets":[0,0,0,0]}],[1],0,[0],[2],[2]],[[{"name":"txt_fwq_wh01_lang","rect":[0,0,44,21],"offset":[0,0],"originalSize":[44,21],"capInsets":[0,0,0,0]}],[1],0,[0],[2],[3]],[[{"name":"txt_fwq_lc01_lang","rect":[0,0,44,20],"offset":[0,0],"originalSize":[44,20],"capInsets":[0,0,0,0]}],[1],0,[0],[2],[4]],[[[12,"choose_server_page"],[13,"choose_server_page",[-8,-9,-10,-11,-12,-13,-14,-15],[[17,0,45,750,1334,-2],[18,-7,-6,-5,-4,-3]],[19,-1],[5,750,1334],[375,667,0,0,0,0,1,1,1,1]],[2,"right_frame",1,[-17],[[4,1,0,-16,[8],9]],[0,"bavZq0sFtHZIvy5rdRDF88",1],[5,624,760],[0,45.489,0,0,0,0,1,1,1,1]],[14,"list",2,[-21],[[-18,[9,8,15,5,400,-20,-19,7]],1,4],[0,"e2Hv8DJXNOCpwuUqWg4Ufk",1],[5,434,740],[95,0,0,0,0,0,1,1,1,1]],[2,"left_frame",1,[-23],[[4,1,0,-22,[12],13]],[0,"adMmqgva1KtbE3sKdlGY5Q",1],[5,190,760],[-217,45,0,0,0,0,1,1,1,1]],[15,"list",4,[-27],[[-24,[9,15,20,5,600,-26,-25,11]],1,4],[0,"d2Am7zxK1LSrfIUrKlkYce",1],[5,190,740]],[2,"red",1,[-29,-30],[[6,1,1,10,-28,[5,83,30]]],[0,"05V7sQM0VJv4zYxRDRi62e",1],[5,83,30],[-180,-370,0,0,0,0,1,1,1,1]],[2,"green",1,[-32,-33],[[6,1,1,10,-31,[5,83,30]]],[0,"0aDeHKXK5H5o+vX9wsGQe/",1],[5,83,30],[0,-370,0,0,0,0,1,1,1,1]],[2,"gray",1,[-35,-36],[[6,1,1,10,-34,[5,83,30]]],[0,"afR15BZmtPE7QIp2ItdpbJ",1],[5,83,30],[180,-370,0,0,0,0,1,1,1,1]],[1,"bg",1,[[4,1,0,-37,[0],1]],[0,"c8izeSoXVLvZO1tMfeZ0Lb",1],[5,674,924],[0,44.9,0,0,0,0,1,1,1,1]],[16,"btn_close",1,[[[20,2,false,-38,[2],3],-39],4,1],[0,"1bqlW07rdEFrVMYLRrv200",1],[5,85,85],[320,475,0,0,0,0,1,1,1,0]],[7,"view",3,[-41],[[10,0,-40,[6]]],[0,"98xGnfYTNLcLFJzOQaJ2/U",1],[5,434,740]],[7,"view",5,[-43],[[10,0,-42,[10]]],[0,"f19KDr+9hJxZytgNCYqRbk",1],[5,190,740]],[21,0.9,3,10],[1,"title",1,[[3,-44,[4],5]],[0,"21WUP0UklFCp7N3BgPu9h2",1],[5,148,28],[0,468,0,0,0,0,1,1,1,1]],[8,"content",11,[0,"49lbPGgeNLtorklbidAOnD",1],[5,434,740],[0,0.5,1],[0,370,0,0,0,0,1,1,1,1]],[11,false,0.75,0.23,null,null,3,15],[8,"content",12,[0,"4ckVKeCL5L47IQZYpcMkPt",1],[5,190,740],[0,0.5,1],[0,370,0,0,0,0,1,1,1,1]],[11,false,0.75,0.23,null,null,5,17],[1,"icon_red",6,[[5,false,-45,[14],15]],[0,"92iTNuP9pEzrvGUTHqcVio",1],[5,29,29],[-27,0,0,0,0,0,1,1,1,1]],[1,"tx",6,[[3,-46,[16],17]],[0,"96ryAAWx9KEqrCZFSoeCh2",1],[5,44,21],[19.5,0,0,0,0,0,1,1,1,1]],[1,"icon_green",7,[[5,false,-47,[18],19]],[0,"fb0LE+h/dPQq7n9BLaBeDR",1],[5,29,29],[-27,0,0,0,0,0,1,1,1,1]],[1,"tx",7,[[3,-48,[20],21]],[0,"d96KyEU5FA4agg2/wTkVOV",1],[5,44,20],[19.5,0,0,0,0,0,1,1,1,1]],[1,"icon_gray",8,[[5,false,-49,[22],23]],[0,"05jIbKocNFWZiQZZ9VgiMu",1],[5,29,29],[-27,0,0,0,0,0,1,1,1,1]],[1,"tx",8,[[3,-50,[24],25]],[0,"4fsYSn0DVBjKv7HpCuUpv3",1],[5,44,21],[19.5,0,0,0,0,0,1,1,1,1]]],0,[0,5,1,0,0,1,0,6,2,0,7,4,0,8,13,0,9,9,0,0,1,0,-1,9,0,-2,10,0,-3,14,0,-4,2,0,-5,4,0,-6,6,0,-7,7,0,-8,8,0,0,2,0,-1,3,0,-1,16,0,3,16,0,0,3,0,-1,11,0,0,4,0,-1,5,0,-1,18,0,3,18,0,0,5,0,-1,12,0,0,6,0,-1,19,0,-2,20,0,0,7,0,-1,21,0,-2,22,0,0,8,0,-1,23,0,-2,24,0,0,9,0,0,10,0,-2,13,0,0,11,0,-1,15,0,0,12,0,-1,17,0,0,14,0,0,19,0,0,20,0,0,21,0,0,22,0,0,23,0,0,24,0,10,1,50],[0,0,0,0,0,0,0,0,0,0,0,0,0,0,0,0,0,0,0,0,0,0,0,0,0,0,13],[-1,1,-1,1,-1,1,-1,4,-1,1,-1,4,-1,1,-1,1,-1,1,-1,1,-1,1,-1,1,-1,1,11],[0,5,0,6,0,7,0,8,0,1,0,9,0,1,0,10,0,11,0,12,0,13,0,14,0,15,0]],[[{"name":"txt_fwq_bm01_lang","rect":[0,0,44,21],"offset":[0,0],"originalSize":[44,21],"capInsets":[0,0,0,0]}],[1],0,[0],[2],[16]]]]