[1,["ae5nkvpoZARYWXPpe4JfOA"],0,[["sp.SkeletonData",["_name","_atlasText","textureNames","_skeletonJson","textures"],-1,3]],[[0,0,1,2,3,4,5]],[[0,"magic2","\nmagic2.png\nsize: 718, 718\nformat: RGBA8888\nfilter: Linear, Linear\nrepeat: none\nhy_magica1\n  rotate: false\n  xy: 142, 3\n  size: 137, 178\n  orig: 137, 178\n  offset: 0, 0\n  index: -1\nhy_magica2\n  rotate: false\n  xy: 0, 5\n  size: 142, 176\n  orig: 142, 176\n  offset: 0, 0\n  index: -1\nhy_magica3\n  rotate: true\n  xy: 422, 571\n  size: 147, 170\n  orig: 147, 170\n  offset: 0, 0\n  index: -1\nhy_magica4\n  rotate: false\n  xy: 0, 181\n  size: 145, 174\n  orig: 145, 174\n  offset: 0, 0\n  index: -1\nhy_magica5\n  rotate: false\n  xy: 279, 20\n  size: 115, 170\n  orig: 115, 170\n  offset: 0, 0\n  index: -1\nhy_magica6\n  rotate: true\n  xy: 322, 235\n  size: 120, 168\n  orig: 120, 168\n  offset: 0, 0\n  index: -1\nhy_magica7\n  rotate: true\n  xy: 145, 234\n  size: 121, 177\n  orig: 121, 177\n  offset: 0, 0\n  index: -1\nlj_magica1\n  rotate: false\n  xy: 696, 522\n  size: 19, 100\n  orig: 19, 100\n  offset: 0, 0\n  index: -1\nlj_magica2\n  rotate: false\n  xy: 696, 622\n  size: 22, 96\n  orig: 22, 96\n  offset: 0, 0\n  index: -1\nlj_magica3\n  rotate: true\n  xy: 490, 257\n  size: 35, 103\n  orig: 35, 103\n  offset: 0, 0\n  index: -1\nmagic_xx1\n  rotate: false\n  xy: 696, 498\n  size: 20, 24\n  orig: 20, 24\n  offset: 0, 0\n  index: -1\nmagic_xx2\n  rotate: true\n  xy: 563, 548\n  size: 23, 25\n  orig: 23, 25\n  offset: 0, 0\n  index: -1\nmagic_xx3\n  rotate: false\n  xy: 696, 473\n  size: 19, 25\n  orig: 19, 25\n  offset: 0, 0\n  index: -1\nmagica1\n  rotate: true\n  xy: 0, 355\n  size: 66, 593\n  orig: 66, 593\n  offset: 0, 0\n  index: -1\nmagica2\n  rotate: true\n  xy: 460, 438\n  size: 63, 87\n  orig: 63, 87\n  offset: 0, 0\n  index: -1\nmagica3\n  rotate: true\n  xy: 258, 430\n  size: 123, 202\n  orig: 123, 202\n  offset: 0, 0\n  index: -1\nmagica4\n  rotate: false\n  xy: 487, 12\n  size: 90, 178\n  orig: 90, 178\n  offset: 0, 0\n  index: -1\nmagica_fg1\n  rotate: false\n  xy: 394, 7\n  size: 93, 183\n  orig: 93, 183\n  offset: 0, 0\n  index: -1\nmagica_fg2\n  rotate: true\n  xy: 460, 501\n  size: 70, 103\n  orig: 70, 103\n  offset: 0, 0\n  index: -1\nmagica_fg3\n  rotate: true\n  xy: 490, 292\n  size: 63, 87\n  orig: 63, 87\n  offset: 0, 0\n  index: -1\nmagica_fg4\n  rotate: true\n  xy: 145, 190\n  size: 44, 379\n  orig: 44, 379\n  offset: 0, 0\n  index: -1\nmagica_fg5\n  rotate: true\n  xy: 258, 553\n  size: 165, 164\n  orig: 165, 164\n  offset: 0, 0\n  index: -1\nmagica_fg6\n  rotate: false\n  xy: 0, 421\n  size: 258, 297\n  orig: 258, 297\n  offset: 0, 0\n  index: -1\nmagicbm1\n  rotate: false\n  xy: 593, 5\n  size: 52, 713\n  orig: 52, 713\n  offset: 0, 0\n  index: -1\nmagicbm2\n  rotate: false\n  xy: 645, 5\n  size: 51, 713\n  orig: 51, 713\n  offset: 0, 0\n  index: -1\n",["magic2.png"],{"skeleton":{"hash":"0iLbT5oWx98","spine":"3.8-from-4.0.64","x":-142.33,"y":-362.2,"width":291.21,"height":792.29},"bones":[{"name":"root"},{"name":"bone","parent":"root","x":0.81,"y":-0.8},{"name":"magic1","parent":"bone","x":-0.81,"y":0.8},{"name":"hy","parent":"magic1","length":119.12,"rotation":94.81,"x":9.98,"y":222.33,"scaleX":1.4423,"scaleY":1.4423,"transform":"noScale"},{"name":"magica2","parent":"magic1","rotation":-0.42,"x":61.15,"y":271.96},{"name":"magica4","parent":"magic1","length":133.73,"rotation":-81.05,"x":-87.36,"y":171.46},{"name":"magica3","parent":"magic1","length":149.11,"rotation":90.34,"x":-79.87,"y":204.39},{"name":"lj_magica1","parent":"magic1","rotation":-0.42,"x":-102.65,"y":171.84},{"name":"magic_xx1","parent":"magic1","rotation":-0.42,"x":1.68,"y":207.01,"scaleX":1.9942,"scaleY":1.9942,"transform":"noScale"},{"name":"lj_magica2","parent":"magic1","rotation":-11.25,"x":-56.63,"y":206.33},{"name":"lj_magica3","parent":"magic1","rotation":73.32,"x":-36.93,"y":223.56},{"name":"lj_magica4","parent":"magic1","rotation":146.23,"x":35.21,"y":253.01},{"name":"lj_magica5","parent":"magic1","rotation":-56.25,"x":-25.15,"y":175.71},{"name":"magica_fg6","parent":"magic1","x":-6.56,"y":241.51},{"name":"magica_fg5","parent":"magic1","x":7.69,"y":244.8,"scaleX":1.7038,"scaleY":1.7038},{"name":"magica_fg7","parent":"magic1","x":3.72,"y":-304.02,"scaleX":0.6882,"scaleY":0.6882,"transform":"noScale"},{"name":"magic_xx2","parent":"magic1","rotation":-0.42,"x":-24.64,"y":217.53,"scaleX":2.4904,"scaleY":2.4904,"transform":"noScale"},{"name":"magic_xx3","parent":"magic1","rotation":-0.42,"x":14.31,"y":196.48,"scaleX":1.9942,"scaleY":1.9942,"transform":"noScale"},{"name":"magic_xx4","parent":"magic1","rotation":-0.42,"x":41.68,"y":219.64,"scaleX":1.9942,"scaleY":1.9942,"transform":"noScale"},{"name":"magic_xx5","parent":"magic1","rotation":-0.42,"x":14.31,"y":196.48,"scaleX":2.6119,"scaleY":2.6119,"transform":"noScale"},{"name":"magic_xx6","parent":"magic1","rotation":-0.42,"x":-5.69,"y":187.01,"scaleX":1.9942,"scaleY":1.9942,"transform":"noScale"},{"name":"magicbm1","parent":"bone","x":-1.84,"y":-40.22,"transform":"noScale"},{"name":"magicbm2","parent":"bone","x":-1.84,"y":-40.22,"transform":"noScale"}],"slots":[{"name":"magica_fg6","bone":"magica_fg6","attachment":"magica_fg6"},{"name":"lj_magica1","bone":"lj_magica1","attachment":"lj_magica1"},{"name":"lj_magica2","bone":"lj_magica2","attachment":"lj_magica1"},{"name":"lj_magica3","bone":"lj_magica3","attachment":"lj_magica1"},{"name":"lj_magica4","bone":"lj_magica4","attachment":"lj_magica1"},{"name":"lj_magica5","bone":"lj_magica5","attachment":"lj_magica1"},{"name":"magica1","bone":"magic1","attachment":"magica1"},{"name":"magic_xx1","bone":"magic_xx1","attachment":"magic_xx1"},{"name":"magic_xx2","bone":"magic_xx2","attachment":"magic_xx2"},{"name":"magic_xx3","bone":"magic_xx3","attachment":"magic_xx3"},{"name":"magic_xx4","bone":"magic_xx4","attachment":"magic_xx1"},{"name":"magic_xx5","bone":"magic_xx5","attachment":"magic_xx1"},{"name":"magic_xx6","bone":"magic_xx6","attachment":"magic_xx2"},{"name":"magica2","bone":"magica2","attachment":"magica2"},{"name":"magica3","bone":"magica3","attachment":"magica3"},{"name":"magica4","bone":"magica4","attachment":"magica4"},{"name":"hy_magica1","bone":"hy","attachment":"hy_magica1"},{"name":"magica_fg1","bone":"magica3","color":"d50d0dff","attachment":"magica_fg1","blend":"additive"},{"name":"magica_fg2","bone":"magica4","color":"d50d0dff","attachment":"magica_fg2","blend":"additive"},{"name":"magica_fg3","bone":"magica2","color":"d50d0dff","attachment":"magica_fg3","blend":"additive"},{"name":"magica_fg4","bone":"magic1","color":"d50d0dff","attachment":"magica_fg4","blend":"additive"},{"name":"magica_fg5","bone":"magica_fg5","color":"ff8c07ff","attachment":"magica_fg5","blend":"additive"},{"name":"magicbm2","bone":"magicbm2"},{"name":"magicbm1","bone":"magicbm1"},{"name":"magica_fg7","bone":"magica_fg7","color":"ff8c07ff","attachment":"magica_fg5","blend":"additive"}],"skins":[{"name":"default","attachments":{"hy_magica1":{"hy_magica1":{"x":54.87,"y":2.76,"rotation":-95.31,"width":137,"height":178},"hy_magica2":{"x":57.19,"y":6.06,"rotation":-95.31,"width":142,"height":176},"hy_magica3":{"x":52.53,"y":10.01,"rotation":-95.31,"width":147,"height":170},"hy_magica4":{"x":52.44,"y":9.01,"rotation":-95.31,"width":145,"height":174},"hy_magica5":{"x":46.72,"y":1.51,"rotation":-95.31,"width":115,"height":170},"hy_magica6":{"x":51.56,"y":-0.45,"rotation":-95.31,"width":120,"height":168},"hy_magica7":{"x":52.01,"y":-0.99,"rotation":-95.31,"width":121,"height":177}},"lj_magica1":{"lj_magica1":{"x":0.26,"y":-2.75,"width":19,"height":100},"lj_magica2":{"x":2.33,"y":-4.75,"width":22,"height":96},"lj_magica3":{"x":4.83,"y":-5.25,"width":35,"height":103}},"lj_magica2":{"lj_magica1":{"x":0.26,"y":-2.75,"width":19,"height":100},"lj_magica2":{"x":2.33,"y":-4.75,"width":22,"height":96},"lj_magica3":{"x":4.83,"y":-5.25,"width":35,"height":103}},"lj_magica3":{"lj_magica1":{"x":0.26,"y":-2.75,"width":19,"height":100},"lj_magica2":{"x":2.33,"y":-4.75,"width":22,"height":96},"lj_magica3":{"x":4.83,"y":-5.25,"width":35,"height":103}},"lj_magica4":{"lj_magica1":{"x":0.26,"y":-2.75,"width":19,"height":100},"lj_magica2":{"x":2.33,"y":-4.75,"width":22,"height":96},"lj_magica3":{"x":4.83,"y":-5.25,"width":35,"height":103}},"lj_magica5":{"lj_magica1":{"x":0.26,"y":-2.75,"width":19,"height":100},"lj_magica2":{"x":2.33,"y":-4.75,"width":22,"height":96},"lj_magica3":{"x":4.83,"y":-5.25,"width":35,"height":103}},"magica1":{"magica1":{"x":12.68,"y":-45.82,"rotation":-0.42,"width":66,"height":593}},"magica2":{"magica2":{"x":5.36,"y":3.87,"width":63,"height":87}},"magica3":{"magica3":{"x":54.48,"y":-0.1,"rotation":-90.76,"width":123,"height":202}},"magica4":{"magica4":{"x":60.81,"y":-3.31,"rotation":80.63,"width":90,"height":178}},"magica_fg1":{"magica_fg1":{"x":62.22,"y":-8.45,"rotation":-90.15,"width":93,"height":183}},"magica_fg2":{"magica_fg2":{"x":26.9,"y":13.48,"rotation":81.24,"width":70,"height":103}},"magica_fg3":{"magica_fg3":{"x":5.37,"y":4.18,"rotation":0.61,"width":63,"height":87}},"magica_fg4":{"magica_fg4":{"x":8.18,"y":18.64,"rotation":0.19,"width":44,"height":379}},"magica_fg5":{"magica_fg5":{"x":0.37,"y":-2.53,"width":165,"height":164}},"magica_fg6":{"magica_fg6":{"x":11.95,"y":-19.39,"width":258,"height":297}},"magica_fg7":{"magica_fg5":{"x":0.37,"y":-2.53,"width":165,"height":164}},"magicbm1":{"magicbm1":{"x":2.47,"y":45.66,"width":52,"height":713},"magicbm2":{"x":2.86,"y":45.66,"width":51,"height":713}},"magicbm2":{"magicbm1":{"x":2.47,"y":45.66,"width":52,"height":713},"magicbm2":{"type":"mesh","hull":10,"uvs":[1,0.9986,1,0.69131,1,0.4621,1,0.26225,0.59411,0.27762,0,0.26923,0,0.45791,0,0.6969,0,1,1,1],"triangles":[6,5,4,4,3,2,6,4,2,6,2,1,1,7,6,7,1,0,8,7,0,8,0,9],"vertices":[28.36,-309.85,28.36,-90.74,28.36,72.68,28.36,215.17,7.66,204.21,-22.64,210.19,-22.64,75.67,-22.64,-94.73,-22.64,-310.84,28.36,-310.84]}},"magic_xx1":{"magic_xx1":{"x":2.01,"y":1.05,"width":20,"height":24},"magic_xx2":{"x":1.68,"y":0.17,"width":23,"height":25},"magic_xx3":{"x":1.89,"y":-1.2,"width":19,"height":25}},"magic_xx2":{"magic_xx1":{"x":2.01,"y":1.05,"width":20,"height":24},"magic_xx2":{"x":1.68,"y":0.17,"width":23,"height":25},"magic_xx3":{"x":1.89,"y":-1.2,"width":19,"height":25}},"magic_xx3":{"magic_xx1":{"x":2.01,"y":1.05,"width":20,"height":24},"magic_xx2":{"x":1.68,"y":0.17,"width":23,"height":25},"magic_xx3":{"x":1.89,"y":-1.2,"width":19,"height":25}},"magic_xx4":{"magic_xx1":{"x":2.01,"y":1.05,"width":20,"height":24},"magic_xx2":{"x":1.68,"y":0.17,"width":23,"height":25},"magic_xx3":{"x":1.89,"y":-1.2,"width":19,"height":25}},"magic_xx5":{"magic_xx1":{"x":2.01,"y":1.05,"width":20,"height":24},"magic_xx2":{"x":1.68,"y":0.17,"width":23,"height":25},"magic_xx3":{"x":1.89,"y":-1.2,"width":19,"height":25}},"magic_xx6":{"magic_xx1":{"x":2.01,"y":1.05,"width":20,"height":24},"magic_xx2":{"x":1.68,"y":0.17,"width":23,"height":25},"magic_xx3":{"x":1.89,"y":-1.2,"width":19,"height":25}}}}],"animations":{"idle1":{"slots":{"hy_magica1":{"attachment":[{"time":0.0667,"name":"hy_magica2"},{"time":0.1,"name":"hy_magica3"},{"time":0.1667,"name":"hy_magica4"},{"time":0.2,"name":"hy_magica5"},{"time":0.2667,"name":"hy_magica6"},{"time":0.3333,"name":"hy_magica7"},{"time":0.3667,"name":"hy_magica1"},{"time":0.4333,"name":"hy_magica2"},{"time":0.5,"name":"hy_magica3"},{"time":0.5333,"name":"hy_magica4"},{"time":0.6,"name":"hy_magica5"},{"time":0.6333,"name":"hy_magica6"},{"time":0.7,"name":"hy_magica7"},{"time":0.7667,"name":"hy_magica1"},{"time":0.8,"name":"hy_magica2"},{"time":0.8667,"name":"hy_magica3"},{"time":0.9333,"name":"hy_magica4"},{"time":0.9667,"name":"hy_magica5"},{"time":1.0333,"name":"hy_magica6"},{"time":1.0667,"name":"hy_magica7"}]},"lj_magica1":{"attachment":[{"time":0.0667,"name":"lj_magica2"},{"time":0.1333,"name":"lj_magica3"},{"time":0.2,"name":"lj_magica1"},{"time":0.2667,"name":"lj_magica2"},{"time":0.3,"name":"lj_magica3"},{"time":0.3667,"name":"lj_magica1"},{"time":0.4333,"name":"lj_magica2"},{"time":0.5,"name":"lj_magica3"},{"time":0.5667,"name":"lj_magica1"},{"time":0.6333,"name":"lj_magica2"},{"time":0.7,"name":"lj_magica3"},{"time":0.7667,"name":"lj_magica1"},{"time":0.8333,"name":"lj_magica2"},{"time":0.8667,"name":"lj_magica3"},{"time":0.9333,"name":"lj_magica1"},{"time":1,"name":"lj_magica2"},{"time":1.0667,"name":"lj_magica3"}]},"lj_magica2":{"attachment":[{"name":"lj_magica2"},{"time":0.0667,"name":"lj_magica3"},{"time":0.1333,"name":"lj_magica1"},{"time":0.2,"name":"lj_magica2"},{"time":0.2333,"name":"lj_magica3"},{"time":0.3,"name":"lj_magica1"},{"time":0.3667,"name":"lj_magica2"},{"time":0.4333,"name":"lj_magica1"},{"time":0.5,"name":"lj_magica2"},{"time":0.5667,"name":"lj_magica3"},{"time":0.6333,"name":"lj_magica1"},{"time":0.7,"name":"lj_magica2"},{"time":0.7333,"name":"lj_magica3"},{"time":0.8,"name":"lj_magica1"},{"time":0.8667,"name":"lj_magica2"},{"time":0.9333,"name":"lj_magica3"},{"time":1,"name":"lj_magica1"}]},"lj_magica3":{"attachment":[{"name":"lj_magica2"},{"time":0.0667,"name":"lj_magica3"},{"time":0.1333,"name":"lj_magica1"},{"time":0.2,"name":"lj_magica2"},{"time":0.2333,"name":"lj_magica3"},{"time":0.3,"name":"lj_magica1"},{"time":0.3667,"name":"lj_magica2"},{"time":0.4333,"name":"lj_magica1"},{"time":0.5,"name":"lj_magica2"},{"time":0.5667,"name":"lj_magica3"},{"time":0.6333,"name":"lj_magica1"},{"time":0.7,"name":"lj_magica2"},{"time":0.7333,"name":"lj_magica3"},{"time":0.8,"name":"lj_magica1"},{"time":0.8667,"name":"lj_magica2"},{"time":0.9333,"name":"lj_magica3"},{"time":1,"name":"lj_magica1"}]},"lj_magica4":{"attachment":[{"name":"lj_magica2"},{"time":0.0667,"name":"lj_magica3"},{"time":0.1333,"name":"lj_magica1"},{"time":0.2,"name":"lj_magica2"},{"time":0.2333,"name":"lj_magica3"},{"time":0.3,"name":"lj_magica1"},{"time":0.3667,"name":"lj_magica2"},{"time":0.4333,"name":"lj_magica1"},{"time":0.5,"name":"lj_magica2"},{"time":0.5667,"name":"lj_magica3"},{"time":0.6333,"name":"lj_magica1"},{"time":0.7,"name":"lj_magica2"},{"time":0.7333,"name":"lj_magica3"},{"time":0.8,"name":"lj_magica1"},{"time":0.8667,"name":"lj_magica2"},{"time":0.9333,"name":"lj_magica3"},{"time":1,"name":"lj_magica1"}]},"lj_magica5":{"attachment":[{"name":"lj_magica2"},{"time":0.0667,"name":"lj_magica3"},{"time":0.1333,"name":"lj_magica1"},{"time":0.2,"name":"lj_magica2"},{"time":0.2333,"name":"lj_magica3"},{"time":0.3,"name":"lj_magica1"},{"time":0.3667,"name":"lj_magica2"},{"time":0.4333,"name":"lj_magica1"},{"time":0.5,"name":"lj_magica2"},{"time":0.5667,"name":"lj_magica3"},{"time":0.6333,"name":"lj_magica1"},{"time":0.7,"name":"lj_magica2"},{"time":0.7333,"name":"lj_magica3"},{"time":0.8,"name":"lj_magica1"},{"time":0.8667,"name":"lj_magica2"},{"time":0.9333,"name":"lj_magica3"},{"time":1,"name":"lj_magica1"}]},"magica_fg1":{"color":[{"color":"ff00003d"},{"time":0.1,"color":"e20000ff"},{"time":0.2,"color":"ff0000ca"},{"time":0.2667,"color":"ff00003d"},{"time":0.3667,"color":"e20000ff"},{"time":0.4667,"color":"ff00007c"},{"time":0.5333,"color":"ff00003d"},{"time":0.6333,"color":"e20000bd"},{"time":0.7333,"color":"ff0000ca"},{"time":0.8333,"color":"ff00003d"},{"time":0.9333,"color":"e20000ff"},{"time":1.0667,"color":"ff00003d"}]},"magica_fg2":{"color":[{"color":"ff00003d"},{"time":0.1,"color":"e20000ff"},{"time":0.2,"color":"ff0000ca"},{"time":0.2667,"color":"ff00003d"},{"time":0.3667,"color":"e20000ff"},{"time":0.4667,"color":"ff00007c"},{"time":0.5333,"color":"ff00003d"},{"time":0.6333,"color":"e20000bd"},{"time":0.7333,"color":"ff0000ca"},{"time":0.8333,"color":"ff00003d"},{"time":0.9333,"color":"e20000ff"},{"time":1.0667,"color":"ff00003d"}]},"magica_fg3":{"color":[{"color":"ff00003d"},{"time":0.1,"color":"e20000ff"},{"time":0.2,"color":"ff0000ca"},{"time":0.2667,"color":"ff00003d"},{"time":0.3667,"color":"e20000ff"},{"time":0.4667,"color":"ff00007c"},{"time":0.5333,"color":"ff00003d"},{"time":0.6333,"color":"e20000bd"},{"time":0.7333,"color":"ff0000ca"},{"time":0.8333,"color":"ff00003d"},{"time":0.9333,"color":"e20000ff"},{"time":1.0667,"color":"ff00003d"}]},"magica_fg4":{"color":[{"color":"ff00003d"},{"time":0.1,"color":"e20000ff"},{"time":0.2,"color":"ff0000ca"},{"time":0.2667,"color":"ff00003d"},{"time":0.3667,"color":"e20000ff"},{"time":0.4667,"color":"ff00007c"},{"time":0.5333,"color":"ff00003d"},{"time":0.6333,"color":"e20000bd"},{"time":0.7333,"color":"ff0000ca"},{"time":0.8333,"color":"ff00003d"},{"time":0.9333,"color":"e20000ff"},{"time":1.0667,"color":"ff00003d"}]},"magica_fg5":{"color":[{"time":0.8,"color":"ff8c07ff"},{"time":0.9333,"color":"ff8c07b1"},{"time":1.0667,"color":"ff8c07ff"}]},"magica_fg6":{"color":[{"color":"69129885"},{"time":0.5333,"color":"691298cb"},{"time":1.0667,"color":"69129885"}]},"magica_fg7":{"color":[{"time":0.8,"color":"ff8c07ff"},{"time":0.9333,"color":"ff8c07b1"},{"time":1.0667,"color":"ff8c07ff"}]},"magic_xx1":{"color":[{"color":"ffffff00"},{"time":0.0667,"color":"ffffffff","curve":"stepped"},{"time":0.6667,"color":"ffffffff"},{"time":0.9667,"color":"ffffff00"}]},"magic_xx2":{"color":[{"color":"ffffffc6"},{"time":0.2333,"color":"ffffff00","curve":"stepped"},{"time":0.3333,"color":"ffffff00"},{"time":0.4,"color":"ffffffff","curve":"stepped"},{"time":1,"color":"ffffffff"},{"time":1.0667,"color":"ffffffc6"}]},"magic_xx3":{"color":[{"color":"ffffff3a"},{"time":0.1,"color":"ffffff00","curve":"stepped"},{"time":0.1333,"color":"ffffff00"},{"time":0.2,"color":"ffffffff","curve":"stepped"},{"time":0.7333,"color":"ffffffff"},{"time":1.0667,"color":"ffffff3a"}]},"magic_xx4":{"color":[{"time":0.3667,"color":"ffffffff"},{"time":0.6667,"color":"ffffff00","curve":"stepped"},{"time":0.7667,"color":"ffffff00"},{"time":0.8333,"color":"ffffffff"}]},"magic_xx5":{"color":[{"time":0.5333,"color":"ffffffff"},{"time":0.8333,"color":"ffffff00","curve":"stepped"},{"time":0.9333,"color":"ffffff00"},{"time":1,"color":"ffffffff"}]},"magic_xx6":{"color":[{"color":"ffffff00","curve":"stepped"},{"time":0.1,"color":"ffffff00"},{"time":0.1667,"color":"ffffffff","curve":"stepped"},{"time":0.7667,"color":"ffffffff"},{"time":1.0667,"color":"ffffff00"}]}},"bones":{"magica2":{"rotate":[{"angle":-0.92},{"time":0.2667,"angle":1.99},{"time":0.8,"angle":-3.83},{"time":1.0667,"angle":-0.92}],"translate":[{},{"time":0.5333,"x":19.25,"y":3.01},{"time":1.0667}]},"magica3":{"rotate":[{"angle":-0.97},{"time":0.2667},{"time":0.8,"angle":-1.93},{"time":1.0667,"angle":-0.97}],"translate":[{},{"time":0.5333,"x":-9.19,"y":17.22},{"time":1.0667}]},"magica4":{"rotate":[{"angle":3.79},{"time":0.2667},{"time":0.8,"angle":7.58},{"time":1.0667,"angle":3.79}],"translate":[{},{"time":0.5333,"x":4.71,"y":-13.18},{"time":1.0667}]},"lj_magica1":{"rotate":[{},{"time":0.5333,"angle":9.68},{"time":1.0667}],"translate":[{},{"time":0.5333,"x":2.73,"y":-10.91},{"time":1.0667}]},"lj_magica2":{"rotate":[{"angle":-6.5},{"time":0.5333,"angle":22.25},{"time":1.0667,"angle":-6.5}],"translate":[{"x":8.2,"y":8.2},{"time":0.5333,"x":-6.06,"y":0.22},{"time":1.0667,"x":8.2,"y":8.2}]},"lj_magica3":{"rotate":[{"angle":-6.5},{"time":0.5333,"angle":-6.97},{"time":1.0667,"angle":-6.5}],"translate":[{"x":8.2,"y":8.2},{"time":0.5333,"x":-6.06,"y":0.22},{"time":1.0667,"x":8.2,"y":8.2}]},"lj_magica4":{"rotate":[{"angle":-6.5},{"time":0.5333,"angle":-18.9},{"time":1.0667,"angle":-6.5}],"translate":[{"x":-2.84,"y":0.84},{"time":0.5333,"x":-1.65,"y":-4.19},{"time":1.0667,"x":-2.84,"y":0.84}]},"lj_magica5":{"rotate":[{"angle":-6.5},{"time":0.5333,"angle":-2.38},{"time":1.0667,"angle":-6.5}],"translate":[{"x":-2.84,"y":0.84},{"time":0.5333,"x":-1.65,"y":-4.19},{"time":1.0667,"x":-2.84,"y":0.84}]},"magica_fg6":{"scale":[{},{"time":0.1333,"x":1.066,"y":1.066},{"time":0.2667},{"time":0.4,"x":1.066,"y":1.066},{"time":0.5333},{"time":0.6667,"x":1.066,"y":1.066},{"time":0.8},{"time":0.9333,"x":1.066,"y":1.066},{"time":1.0667}]},"magica_fg5":{"scale":[{},{"time":0.1333,"x":1.066,"y":1.066},{"time":0.2667},{"time":0.4,"x":1.066,"y":1.066},{"time":0.5333},{"time":0.6667,"x":1.066,"y":1.066},{"time":0.8},{"time":0.9333,"x":1.066,"y":1.066},{"time":1.0667}]},"magica_fg7":{"scale":[{},{"time":0.1333,"x":1.066,"y":1.066},{"time":0.2667},{"time":0.4,"x":1.066,"y":1.066},{"time":0.5333},{"time":0.6667,"x":1.066,"y":1.066},{"time":0.8},{"time":0.9333,"x":1.066,"y":1.066},{"time":1.0667}]},"magic_xx1":{"rotate":[{},{"time":0.9667,"angle":-428.9},{"time":1.0667}],"translate":[{"x":16.1,"y":-8.59},{"time":0.5,"x":26.65,"y":-149.06},{"time":0.9667,"x":54.75,"y":-282.32},{"time":1.0667}],"scale":[{"x":2.271,"y":2.271},{"time":0.9667,"x":0.58,"y":0.58},{"time":1.0667}]},"magic_xx2":{"rotate":[{"angle":-325.37},{"time":0.2333,"angle":-428.9},{"time":0.3333},{"time":1.0667,"angle":-325.37}],"translate":[{"x":-31.94,"y":-175.53},{"time":0.2333,"x":-47.23,"y":-228.65},{"time":0.3333,"x":16.1,"y":-8.59},{"time":1.0667,"x":-31.94,"y":-175.53}],"scale":[{"x":1.548,"y":1.548},{"time":0.2333,"x":0.58,"y":0.58},{"time":0.3333},{"time":1.0667,"x":0.682,"y":0.682}]},"magic_xx3":{"rotate":[{"angle":-387.39},{"time":0.1,"angle":-428.9},{"time":0.1333},{"time":1.0667,"angle":-387.39}],"translate":[{"x":-33.94,"y":-298.39},{"time":0.1,"x":-37.57,"y":-329.55},{"time":0.1333,"y":-7.51},{"time":1.0667,"x":-33.94,"y":-298.39}],"scale":[{"x":1.41,"y":1.41},{"time":0.1,"x":0.58,"y":0.58},{"time":0.1333},{"time":1.0667,"x":0.621,"y":0.621}]},"magic_xx4":{"rotate":[{"angle":-133.11},{"time":0.6667,"angle":-428.9},{"time":0.7667},{"time":1.0667,"angle":-133.11}],"translate":[{"x":11.1,"y":-78.88},{"time":0.6667,"y":-235.09},{"time":0.7667,"x":16.1,"y":-8.59},{"time":1.0667,"x":11.1,"y":-78.88}],"scale":[{"x":1.975,"y":1.975},{"time":0.6667,"x":0.58,"y":0.58},{"time":0.7667},{"time":1.0667,"x":0.87,"y":0.87}]},"magic_xx5":{"rotate":[{"angle":-59.16},{"time":0.8333,"angle":-428.9},{"time":0.9333},{"time":1.0667,"angle":-59.16}],"translate":[{"x":4.7,"y":-29.02},{"time":0.8333,"x":-66.55,"y":-156.72},{"time":0.9333,"x":16.1,"y":-8.59},{"time":1.0667,"x":4.7,"y":-29.02}],"scale":[{"x":2.139,"y":2.139},{"time":0.8333,"x":0.58,"y":0.58},{"time":0.9333},{"time":1.0667,"x":0.942,"y":0.942}]},"magic_xx6":{"rotate":[{"angle":-428.9},{"time":0.1},{"time":1.0667,"angle":-428.9}],"translate":[{"x":60.11,"y":-168.53},{"time":0.1,"x":16.1,"y":-8.59},{"time":1.0667,"x":60.11,"y":-168.53}],"scale":[{"x":1.318,"y":1.318},{"time":0.1},{"time":1.0667,"x":0.58,"y":0.58}]}}},"idle2":{"slots":{"hy_magica1":{"attachment":[{"time":0.0667,"name":"hy_magica2"},{"time":0.1,"name":"hy_magica3"},{"time":0.1667,"name":"hy_magica4"},{"time":0.2,"name":"hy_magica5"},{"time":0.2667,"name":"hy_magica6"},{"time":0.3333,"name":"hy_magica7"},{"time":0.3667,"name":"hy_magica1"},{"time":0.4333,"name":"hy_magica2"},{"time":0.5,"name":"hy_magica3"},{"time":0.5333,"name":"hy_magica4"},{"time":0.6,"name":"hy_magica5"},{"time":0.6333,"name":"hy_magica6"},{"time":0.7,"name":"hy_magica7"},{"time":0.7667,"name":"hy_magica1"},{"time":0.8,"name":"hy_magica2"},{"time":0.8667,"name":"hy_magica3"},{"time":0.9333,"name":"hy_magica4"},{"time":0.9667,"name":"hy_magica5"},{"time":1.0333,"name":"hy_magica6"},{"time":1.0667,"name":"hy_magica1"},{"time":1.1333,"name":"hy_magica2"},{"time":1.1667,"name":"hy_magica3"},{"time":1.2333,"name":"hy_magica4"},{"time":1.2667,"name":"hy_magica5"},{"time":1.3333,"name":"hy_magica6"},{"time":1.4,"name":"hy_magica7"},{"time":1.4333,"name":"hy_magica1"},{"time":1.5,"name":"hy_magica2"},{"time":1.5667,"name":"hy_magica3"},{"time":1.6,"name":"hy_magica4"},{"time":1.6667,"name":"hy_magica5"},{"time":1.7,"name":"hy_magica6"},{"time":1.7667,"name":"hy_magica7"},{"time":1.8333,"name":"hy_magica1"},{"time":1.8667,"name":"hy_magica2"},{"time":1.9333,"name":"hy_magica3"},{"time":2,"name":"hy_magica4"},{"time":2.0333,"name":"hy_magica5"},{"time":2.1,"name":"hy_magica6"},{"time":2.1333,"name":"hy_magica7"}]},"lj_magica1":{"attachment":[{"time":0.0667,"name":"lj_magica2"},{"time":0.1333,"name":"lj_magica3"},{"time":0.2,"name":"lj_magica1"},{"time":0.2667,"name":"lj_magica2"},{"time":0.3,"name":"lj_magica3"},{"time":0.3667,"name":"lj_magica1"},{"time":0.4333,"name":"lj_magica2"},{"time":0.5,"name":"lj_magica3"},{"time":0.5667,"name":"lj_magica1"},{"time":0.6333,"name":"lj_magica2"},{"time":0.7,"name":"lj_magica3"},{"time":0.7667,"name":"lj_magica1"},{"time":0.8333,"name":"lj_magica2"},{"time":0.8667,"name":"lj_magica3"},{"time":0.9333,"name":"lj_magica1"},{"time":1,"name":"lj_magica2"},{"time":1.0667,"name":"lj_magica1"},{"time":1.1333,"name":"lj_magica2"},{"time":1.2,"name":"lj_magica3"},{"time":1.2667,"name":"lj_magica1"},{"time":1.3333,"name":"lj_magica2"},{"time":1.3667,"name":"lj_magica3"},{"time":1.4333,"name":"lj_magica1"},{"time":1.5,"name":"lj_magica2"},{"time":1.5667,"name":"lj_magica3"},{"time":1.6333,"name":"lj_magica1"},{"time":1.7,"name":"lj_magica2"},{"time":1.7667,"name":"lj_magica3"},{"time":1.8333,"name":"lj_magica1"},{"time":1.9,"name":"lj_magica2"},{"time":1.9333,"name":"lj_magica3"},{"time":2,"name":"lj_magica1"},{"time":2.0667,"name":"lj_magica2"},{"time":2.1333,"name":"lj_magica3"}]},"lj_magica2":{"attachment":[{"name":"lj_magica2"},{"time":0.0667,"name":"lj_magica3"},{"time":0.1333,"name":"lj_magica1"},{"time":0.2,"name":"lj_magica2"},{"time":0.2333,"name":"lj_magica3"},{"time":0.3,"name":"lj_magica1"},{"time":0.3667,"name":"lj_magica2"},{"time":0.4333,"name":"lj_magica1"},{"time":0.5,"name":"lj_magica2"},{"time":0.5667,"name":"lj_magica3"},{"time":0.6333,"name":"lj_magica1"},{"time":0.7,"name":"lj_magica2"},{"time":0.7333,"name":"lj_magica3"},{"time":0.8,"name":"lj_magica1"},{"time":0.8667,"name":"lj_magica2"},{"time":0.9333,"name":"lj_magica3"},{"time":1,"name":"lj_magica1"},{"time":1.0667,"name":"lj_magica2"},{"time":1.1333,"name":"lj_magica3"},{"time":1.2,"name":"lj_magica1"},{"time":1.2667,"name":"lj_magica2"},{"time":1.3,"name":"lj_magica3"},{"time":1.3667,"name":"lj_magica1"},{"time":1.4333,"name":"lj_magica2"},{"time":1.5,"name":"lj_magica1"},{"time":1.5667,"name":"lj_magica2"},{"time":1.6333,"name":"lj_magica3"},{"time":1.7,"name":"lj_magica1"},{"time":1.7667,"name":"lj_magica2"},{"time":1.8,"name":"lj_magica3"},{"time":1.8667,"name":"lj_magica1"},{"time":1.9333,"name":"lj_magica2"},{"time":2,"name":"lj_magica3"},{"time":2.0667,"name":"lj_magica1"}]},"lj_magica3":{"attachment":[{"name":"lj_magica2"},{"time":0.0667,"name":"lj_magica3"},{"time":0.1333,"name":"lj_magica1"},{"time":0.2,"name":"lj_magica2"},{"time":0.2333,"name":"lj_magica3"},{"time":0.3,"name":"lj_magica1"},{"time":0.3667,"name":"lj_magica2"},{"time":0.4333,"name":"lj_magica1"},{"time":0.5,"name":"lj_magica2"},{"time":0.5667,"name":"lj_magica3"},{"time":0.6333,"name":"lj_magica1"},{"time":0.7,"name":"lj_magica2"},{"time":0.7333,"name":"lj_magica3"},{"time":0.8,"name":"lj_magica1"},{"time":0.8667,"name":"lj_magica2"},{"time":0.9333,"name":"lj_magica3"},{"time":1,"name":"lj_magica1"},{"time":1.0667,"name":"lj_magica2"},{"time":1.1333,"name":"lj_magica3"},{"time":1.2,"name":"lj_magica1"},{"time":1.2667,"name":"lj_magica2"},{"time":1.3,"name":"lj_magica3"},{"time":1.3667,"name":"lj_magica1"},{"time":1.4333,"name":"lj_magica2"},{"time":1.5,"name":"lj_magica1"},{"time":1.5667,"name":"lj_magica2"},{"time":1.6333,"name":"lj_magica3"},{"time":1.7,"name":"lj_magica1"},{"time":1.7667,"name":"lj_magica2"},{"time":1.8,"name":"lj_magica3"},{"time":1.8667,"name":"lj_magica1"},{"time":1.9333,"name":"lj_magica2"},{"time":2,"name":"lj_magica3"},{"time":2.0667,"name":"lj_magica1"}]},"lj_magica4":{"attachment":[{"name":"lj_magica2"},{"time":0.0667,"name":"lj_magica3"},{"time":0.1333,"name":"lj_magica1"},{"time":0.2,"name":"lj_magica2"},{"time":0.2333,"name":"lj_magica3"},{"time":0.3,"name":"lj_magica1"},{"time":0.3667,"name":"lj_magica2"},{"time":0.4333,"name":"lj_magica1"},{"time":0.5,"name":"lj_magica2"},{"time":0.5667,"name":"lj_magica3"},{"time":0.6333,"name":"lj_magica1"},{"time":0.7,"name":"lj_magica2"},{"time":0.7333,"name":"lj_magica3"},{"time":0.8,"name":"lj_magica1"},{"time":0.8667,"name":"lj_magica2"},{"time":0.9333,"name":"lj_magica3"},{"time":1,"name":"lj_magica1"},{"time":1.0667,"name":"lj_magica2"},{"time":1.1333,"name":"lj_magica3"},{"time":1.2,"name":"lj_magica1"},{"time":1.2667,"name":"lj_magica2"},{"time":1.3,"name":"lj_magica3"},{"time":1.3667,"name":"lj_magica1"},{"time":1.4333,"name":"lj_magica2"},{"time":1.5,"name":"lj_magica1"},{"time":1.5667,"name":"lj_magica2"},{"time":1.6333,"name":"lj_magica3"},{"time":1.7,"name":"lj_magica1"},{"time":1.7667,"name":"lj_magica2"},{"time":1.8,"name":"lj_magica3"},{"time":1.8667,"name":"lj_magica1"},{"time":1.9333,"name":"lj_magica2"},{"time":2,"name":"lj_magica3"},{"time":2.0667,"name":"lj_magica1"}]},"lj_magica5":{"attachment":[{"name":"lj_magica2"},{"time":0.0667,"name":"lj_magica3"},{"time":0.1333,"name":"lj_magica1"},{"time":0.2,"name":"lj_magica2"},{"time":0.2333,"name":"lj_magica3"},{"time":0.3,"name":"lj_magica1"},{"time":0.3667,"name":"lj_magica2"},{"time":0.4333,"name":"lj_magica1"},{"time":0.5,"name":"lj_magica2"},{"time":0.5667,"name":"lj_magica3"},{"time":0.6333,"name":"lj_magica1"},{"time":0.7,"name":"lj_magica2"},{"time":0.7333,"name":"lj_magica3"},{"time":0.8,"name":"lj_magica1"},{"time":0.8667,"name":"lj_magica2"},{"time":0.9333,"name":"lj_magica3"},{"time":1,"name":"lj_magica1"},{"time":1.0667,"name":"lj_magica2"},{"time":1.1333,"name":"lj_magica3"},{"time":1.2,"name":"lj_magica1"},{"time":1.2667,"name":"lj_magica2"},{"time":1.3,"name":"lj_magica3"},{"time":1.3667,"name":"lj_magica1"},{"time":1.4333,"name":"lj_magica2"},{"time":1.5,"name":"lj_magica1"},{"time":1.5667,"name":"lj_magica2"},{"time":1.6333,"name":"lj_magica3"},{"time":1.7,"name":"lj_magica1"},{"time":1.7667,"name":"lj_magica2"},{"time":1.8,"name":"lj_magica3"},{"time":1.8667,"name":"lj_magica1"},{"time":1.9333,"name":"lj_magica2"},{"time":2,"name":"lj_magica3"},{"time":2.0667,"name":"lj_magica1"}]},"magica_fg1":{"color":[{"color":"ff00003d"},{"time":0.1,"color":"e20000ff"},{"time":0.2,"color":"ff0000ca"},{"time":0.2667,"color":"ff00003d"},{"time":0.3667,"color":"e20000ff"},{"time":0.4667,"color":"ff00007c"},{"time":0.5333,"color":"ff00003d"},{"time":0.6333,"color":"e20000bd"},{"time":0.7333,"color":"ff0000ca"},{"time":0.8333,"color":"ff00003d"},{"time":0.9333,"color":"e20000ff"},{"time":1.0667,"color":"ff00003d"},{"time":1.1667,"color":"e20000ff"},{"time":1.2667,"color":"ff0000ca"},{"time":1.3333,"color":"ff00003d"},{"time":1.4333,"color":"e20000ff"},{"time":1.5333,"color":"ff00007c"},{"time":1.6,"color":"ff00003d"},{"time":1.7,"color":"e20000bd"},{"time":1.8,"color":"ff0000ca"},{"time":1.9,"color":"ff00003d"},{"time":2,"color":"e20000ff"},{"time":2.1333,"color":"ff00003d"}]},"magica_fg2":{"color":[{"color":"ff00003d"},{"time":0.1,"color":"e20000ff"},{"time":0.2,"color":"ff0000ca"},{"time":0.2667,"color":"ff00003d"},{"time":0.3667,"color":"e20000ff"},{"time":0.4667,"color":"ff00007c"},{"time":0.5333,"color":"ff00003d"},{"time":0.6333,"color":"e20000bd"},{"time":0.7333,"color":"ff0000ca"},{"time":0.8333,"color":"ff00003d"},{"time":0.9333,"color":"e20000ff"},{"time":1.0667,"color":"ff00003d"},{"time":1.1667,"color":"e20000ff"},{"time":1.2667,"color":"ff0000ca"},{"time":1.3333,"color":"ff00003d"},{"time":1.4333,"color":"e20000ff"},{"time":1.5333,"color":"ff00007c"},{"time":1.6,"color":"ff00003d"},{"time":1.7,"color":"e20000bd"},{"time":1.8,"color":"ff0000ca"},{"time":1.9,"color":"ff00003d"},{"time":2,"color":"e20000ff"},{"time":2.1333,"color":"ff00003d"}]},"magica_fg3":{"color":[{"color":"ff00003d"},{"time":0.1,"color":"e20000ff"},{"time":0.2,"color":"ff0000ca"},{"time":0.2667,"color":"ff00003d"},{"time":0.3667,"color":"e20000ff"},{"time":0.4667,"color":"ff00007c"},{"time":0.5333,"color":"ff00003d"},{"time":0.6333,"color":"e20000bd"},{"time":0.7333,"color":"ff0000ca"},{"time":0.8333,"color":"ff00003d"},{"time":0.9333,"color":"e20000ff"},{"time":1.0667,"color":"ff00003d"},{"time":1.1667,"color":"e20000ff"},{"time":1.2667,"color":"ff0000ca"},{"time":1.3333,"color":"ff00003d"},{"time":1.4333,"color":"e20000ff"},{"time":1.5333,"color":"ff00007c"},{"time":1.6,"color":"ff00003d"},{"time":1.7,"color":"e20000bd"},{"time":1.8,"color":"ff0000ca"},{"time":1.9,"color":"ff00003d"},{"time":2,"color":"e20000ff"},{"time":2.1333,"color":"ff00003d"}]},"magica_fg4":{"color":[{"color":"ff00003d"},{"time":0.1,"color":"e20000ff"},{"time":0.2,"color":"ff0000ca"},{"time":0.2667,"color":"ff00003d"},{"time":0.3667,"color":"e20000ff"},{"time":0.4667,"color":"ff00007c"},{"time":0.5333,"color":"ff00003d"},{"time":0.6333,"color":"e20000bd"},{"time":0.7333,"color":"ff0000ca"},{"time":0.8333,"color":"ff00003d"},{"time":0.9333,"color":"e20000ff"},{"time":1.0667,"color":"ff00003d"},{"time":1.1667,"color":"e20000ff"},{"time":1.2667,"color":"ff0000ca"},{"time":1.3333,"color":"ff00003d"},{"time":1.4333,"color":"e20000ff"},{"time":1.5333,"color":"ff00007c"},{"time":1.6,"color":"ff00003d"},{"time":1.7,"color":"e20000bd"},{"time":1.8,"color":"ff0000ca"},{"time":1.9,"color":"ff00003d"},{"time":2,"color":"e20000ff"},{"time":2.1333,"color":"ff00003d"}]},"magica_fg5":{"color":[{"time":0.8,"color":"ff8c07ff"},{"time":0.9333,"color":"ff8c07b1"},{"time":1.0667,"color":"ff8c07ff","curve":"stepped"},{"time":1.8667,"color":"ff8c07ff"},{"time":2,"color":"ff8c07b1"},{"time":2.1333,"color":"ff8c07ff"}]},"magica_fg6":{"color":[{"color":"69129885"},{"time":0.5333,"color":"691298cb"},{"time":1.0667,"color":"69129885"},{"time":1.6,"color":"691298cb"},{"time":2.1333,"color":"69129885"}]},"magica_fg7":{"color":[{"time":0.8,"color":"ff8c07ff"},{"time":0.9333,"color":"ff8c07b1"},{"time":1.0667,"color":"ff8c07ff","curve":"stepped"},{"time":1.8667,"color":"ff8c07ff"},{"time":2,"color":"ff8c07b1"},{"time":2.1333,"color":"ff8c07ff"}]},"magic_xx1":{"color":[{"color":"ffffff00"},{"time":0.0667,"color":"ffffffff","curve":"stepped"},{"time":0.6667,"color":"ffffffff"},{"time":0.9667,"color":"ffffff00","curve":"stepped"},{"time":1.0667,"color":"ffffff00"},{"time":1.1333,"color":"ffffffff","curve":"stepped"},{"time":1.7333,"color":"ffffffff"},{"time":2.0333,"color":"ffffff00"}]},"magic_xx2":{"color":[{"color":"ffffffc6"},{"time":0.2333,"color":"ffffff00","curve":"stepped"},{"time":0.3333,"color":"ffffff00"},{"time":0.4,"color":"ffffffff","curve":"stepped"},{"time":1,"color":"ffffffff"},{"time":1.0667,"color":"ffffffc6"},{"time":1.3,"color":"ffffff00","curve":"stepped"},{"time":1.4,"color":"ffffff00"},{"time":1.4667,"color":"ffffffff","curve":"stepped"},{"time":2.0667,"color":"ffffffff"},{"time":2.1333,"color":"ffffffc6"}]},"magic_xx3":{"color":[{"color":"ffffff3a"},{"time":0.1,"color":"ffffff00","curve":"stepped"},{"time":0.1333,"color":"ffffff00"},{"time":0.2,"color":"ffffffff","curve":"stepped"},{"time":0.7333,"color":"ffffffff"},{"time":1.0667,"color":"ffffff3a"},{"time":1.1667,"color":"ffffff00","curve":"stepped"},{"time":1.2,"color":"ffffff00"},{"time":1.2667,"color":"ffffffff","curve":"stepped"},{"time":1.8,"color":"ffffffff"},{"time":2.1333,"color":"ffffff3a"}]},"magic_xx4":{"color":[{"time":0.3667,"color":"ffffffff"},{"time":0.6667,"color":"ffffff00","curve":"stepped"},{"time":0.7667,"color":"ffffff00"},{"time":0.8333,"color":"ffffffff","curve":"stepped"},{"time":1.4333,"color":"ffffffff"},{"time":1.7333,"color":"ffffff00","curve":"stepped"},{"time":1.8333,"color":"ffffff00"},{"time":1.9,"color":"ffffffff"}]},"magic_xx5":{"color":[{"time":0.5333,"color":"ffffffff"},{"time":0.8333,"color":"ffffff00","curve":"stepped"},{"time":0.9333,"color":"ffffff00"},{"time":1,"color":"ffffffff","curve":"stepped"},{"time":1.6,"color":"ffffffff"},{"time":1.9,"color":"ffffff00","curve":"stepped"},{"time":2,"color":"ffffff00"},{"time":2.0667,"color":"ffffffff"}]},"magic_xx6":{"color":[{"color":"ffffff00","curve":"stepped"},{"time":0.1,"color":"ffffff00"},{"time":0.1667,"color":"ffffffff","curve":"stepped"},{"time":0.7667,"color":"ffffffff"},{"time":1.0667,"color":"ffffff00","curve":"stepped"},{"time":1.1667,"color":"ffffff00"},{"time":1.2333,"color":"ffffffff","curve":"stepped"},{"time":1.8333,"color":"ffffffff"},{"time":2.1333,"color":"ffffff00"}]}},"bones":{"magica2":{"rotate":[{"angle":-0.92},{"time":0.2667,"angle":1.99},{"time":0.8,"angle":-3.83},{"time":1.0667,"angle":-0.92},{"time":1.3333,"angle":1.99},{"time":1.8667,"angle":-3.83},{"time":2.1333,"angle":-0.92}],"translate":[{},{"time":0.5333,"x":19.25,"y":3.01},{"time":1.0667},{"time":1.6,"x":19.25,"y":3.01},{"time":2.1333}]},"magica3":{"rotate":[{"angle":-0.97},{"time":0.2667},{"time":0.8,"angle":-1.93},{"time":1.0667,"angle":-0.97},{"time":1.3333},{"time":1.8667,"angle":-1.93},{"time":2.1333,"angle":-0.97}],"translate":[{},{"time":0.5333,"x":-9.19,"y":17.22},{"time":1.0667},{"time":1.6,"x":-9.19,"y":17.22},{"time":2.1333}]},"magica4":{"rotate":[{"angle":3.79},{"time":0.2667},{"time":0.8,"angle":7.58},{"time":1.0667,"angle":3.79},{"time":1.3333},{"time":1.8667,"angle":7.58},{"time":2.1333,"angle":3.79}],"translate":[{},{"time":0.5333,"x":4.71,"y":-13.18},{"time":1.0667},{"time":1.6,"x":4.71,"y":-13.18},{"time":2.1333}]},"lj_magica1":{"rotate":[{},{"time":0.5333,"angle":9.68},{"time":1.0667},{"time":1.6,"angle":9.68},{"time":2.1333}],"translate":[{},{"time":0.5333,"x":2.73,"y":-10.91},{"time":1.0667},{"time":1.6,"x":2.73,"y":-10.91},{"time":2.1333}]},"lj_magica2":{"rotate":[{"angle":-6.5},{"time":0.5333,"angle":22.25},{"time":1.0667,"angle":-6.5},{"time":1.6,"angle":22.25},{"time":2.1333,"angle":-6.5}],"translate":[{"x":8.2,"y":8.2},{"time":0.5333,"x":-6.06,"y":0.22},{"time":1.0667,"x":8.2,"y":8.2},{"time":1.6,"x":-6.06,"y":0.22},{"time":2.1333,"x":8.2,"y":8.2}]},"lj_magica3":{"rotate":[{"angle":-6.5},{"time":0.5333,"angle":-6.97},{"time":1.0667,"angle":-6.5},{"time":1.6,"angle":-6.97},{"time":2.1333,"angle":-6.5}],"translate":[{"x":8.2,"y":8.2},{"time":0.5333,"x":-6.06,"y":0.22},{"time":1.0667,"x":8.2,"y":8.2},{"time":1.6,"x":-6.06,"y":0.22},{"time":2.1333,"x":8.2,"y":8.2}]},"lj_magica4":{"rotate":[{"angle":-6.5},{"time":0.5333,"angle":-18.9},{"time":1.0667,"angle":-6.5},{"time":1.6,"angle":-18.9},{"time":2.1333,"angle":-6.5}],"translate":[{"x":-2.84,"y":0.84},{"time":0.5333,"x":-1.65,"y":-4.19},{"time":1.0667,"x":-2.84,"y":0.84},{"time":1.6,"x":-1.65,"y":-4.19},{"time":2.1333,"x":-2.84,"y":0.84}]},"lj_magica5":{"rotate":[{"angle":-6.5},{"time":0.5333,"angle":-2.38},{"time":1.0667,"angle":-6.5},{"time":1.6,"angle":-2.38},{"time":2.1333,"angle":-6.5}],"translate":[{"x":-2.84,"y":0.84},{"time":0.5333,"x":-1.65,"y":-4.19},{"time":1.0667,"x":-2.84,"y":0.84},{"time":1.6,"x":-1.65,"y":-4.19},{"time":2.1333,"x":-2.84,"y":0.84}]},"magica_fg6":{"scale":[{},{"time":0.1333,"x":1.066,"y":1.066},{"time":0.2667},{"time":0.4,"x":1.066,"y":1.066},{"time":0.5333},{"time":0.6667,"x":1.066,"y":1.066},{"time":0.8},{"time":0.9333,"x":1.066,"y":1.066},{"time":1.0667},{"time":1.2,"x":1.066,"y":1.066},{"time":1.3333},{"time":1.4667,"x":1.066,"y":1.066},{"time":1.6},{"time":1.7333,"x":1.066,"y":1.066},{"time":1.8667},{"time":2,"x":1.066,"y":1.066},{"time":2.1333}]},"magica_fg5":{"scale":[{},{"time":0.1333,"x":1.066,"y":1.066},{"time":0.2667},{"time":0.4,"x":1.066,"y":1.066},{"time":0.5333},{"time":0.6667,"x":1.066,"y":1.066},{"time":0.8},{"time":0.9333,"x":1.066,"y":1.066},{"time":1.0667},{"time":1.2,"x":1.066,"y":1.066},{"time":1.3333},{"time":1.4667,"x":1.066,"y":1.066},{"time":1.6},{"time":1.7333,"x":1.066,"y":1.066},{"time":1.8667},{"time":2,"x":1.066,"y":1.066},{"time":2.1333}]},"magica_fg7":{"scale":[{},{"time":0.1333,"x":1.066,"y":1.066},{"time":0.2667},{"time":0.4,"x":1.066,"y":1.066},{"time":0.5333},{"time":0.6667,"x":1.066,"y":1.066},{"time":0.8},{"time":0.9333,"x":1.066,"y":1.066},{"time":1.0667},{"time":1.2,"x":1.066,"y":1.066},{"time":1.3333},{"time":1.4667,"x":1.066,"y":1.066},{"time":1.6},{"time":1.7333,"x":1.066,"y":1.066},{"time":1.8667},{"time":2,"x":1.066,"y":1.066},{"time":2.1333}]},"magic_xx1":{"rotate":[{},{"time":0.9667,"angle":-428.9},{"time":1.0667},{"time":2.0333,"angle":-428.9},{"time":2.1333}],"translate":[{"x":16.1,"y":-8.59},{"time":0.5,"x":26.65,"y":-149.06},{"time":0.9667,"x":54.75,"y":-282.32},{"time":1.0667,"x":16.1,"y":-8.59},{"time":1.5667,"x":26.65,"y":-149.06},{"time":2.0333,"x":54.75,"y":-282.32},{"time":2.1333}],"scale":[{"x":2.271,"y":2.271},{"time":0.9667,"x":0.58,"y":0.58},{"time":1.0667,"x":2.271,"y":2.271},{"time":2.0333,"x":0.58,"y":0.58},{"time":2.1333}]},"magic_xx2":{"rotate":[{"angle":-325.37},{"time":0.2333,"angle":-428.9},{"time":0.3333},{"time":1.0667,"angle":-325.37},{"time":1.3,"angle":-428.9},{"time":1.4},{"time":2.1333,"angle":-325.37}],"translate":[{"x":-31.94,"y":-175.53},{"time":0.2333,"x":-47.23,"y":-228.65},{"time":0.3333,"x":16.1,"y":-8.59},{"time":1.0667,"x":-31.94,"y":-175.53},{"time":1.3,"x":-47.23,"y":-228.65},{"time":1.4,"x":16.1,"y":-8.59},{"time":2.1333,"x":-31.94,"y":-175.53}],"scale":[{"x":1.548,"y":1.548},{"time":0.2333,"x":0.58,"y":0.58},{"time":0.3333},{"time":1.0667,"x":1.548,"y":1.548},{"time":1.3,"x":0.58,"y":0.58},{"time":1.4},{"time":2.1333,"x":0.682,"y":0.682}]},"magic_xx3":{"rotate":[{"angle":-387.39},{"time":0.1,"angle":-428.9},{"time":0.1333},{"time":1.0667,"angle":-387.39},{"time":1.1667,"angle":-428.9},{"time":1.2},{"time":2.1333,"angle":-387.39}],"translate":[{"x":-33.94,"y":-298.39},{"time":0.1,"x":-37.57,"y":-329.55},{"time":0.1333,"y":-7.51},{"time":1.0667,"x":-33.94,"y":-298.39},{"time":1.1667,"x":-37.57,"y":-329.55},{"time":1.2,"y":-7.51},{"time":2.1333,"x":-33.94,"y":-298.39}],"scale":[{"x":1.41,"y":1.41},{"time":0.1,"x":0.58,"y":0.58},{"time":0.1333},{"time":1.0667,"x":1.41,"y":1.41},{"time":1.1667,"x":0.58,"y":0.58},{"time":1.2},{"time":2.1333,"x":0.621,"y":0.621}]},"magic_xx4":{"rotate":[{"angle":-133.11},{"time":0.6667,"angle":-428.9},{"time":0.7667},{"time":1.0667,"angle":-133.11},{"time":1.7333,"angle":-428.9},{"time":1.8333},{"time":2.1333,"angle":-133.11}],"translate":[{"x":11.1,"y":-78.88},{"time":0.6667,"y":-235.09},{"time":0.7667,"x":16.1,"y":-8.59},{"time":1.0667,"x":11.1,"y":-78.88},{"time":1.7333,"y":-235.09},{"time":1.8333,"x":16.1,"y":-8.59},{"time":2.1333,"x":11.1,"y":-78.88}],"scale":[{"x":1.975,"y":1.975},{"time":0.6667,"x":0.58,"y":0.58},{"time":0.7667},{"time":1.0667,"x":1.975,"y":1.975},{"time":1.7333,"x":0.58,"y":0.58},{"time":1.8333},{"time":2.1333,"x":0.87,"y":0.87}]},"magic_xx5":{"rotate":[{"angle":-59.16},{"time":0.8333,"angle":-428.9},{"time":0.9333},{"time":1.0667,"angle":-59.16},{"time":1.9,"angle":-428.9},{"time":2},{"time":2.1333,"angle":-59.16}],"translate":[{"x":4.7,"y":-29.02},{"time":0.8333,"x":-66.55,"y":-156.72},{"time":0.9333,"x":16.1,"y":-8.59},{"time":1.0667,"x":4.7,"y":-29.02},{"time":1.9,"x":-66.55,"y":-156.72},{"time":2,"x":16.1,"y":-8.59},{"time":2.1333,"x":4.7,"y":-29.02}],"scale":[{"x":2.139,"y":2.139},{"time":0.8333,"x":0.58,"y":0.58},{"time":0.9333},{"time":1.0667,"x":2.139,"y":2.139},{"time":1.9,"x":0.58,"y":0.58},{"time":2},{"time":2.1333,"x":0.942,"y":0.942}]},"magic_xx6":{"rotate":[{"angle":-428.9},{"time":0.1},{"time":1.0667,"angle":-428.9},{"time":1.1667},{"time":2.1333,"angle":-428.9}],"translate":[{"x":60.11,"y":-168.53},{"time":0.1,"x":16.1,"y":-8.59},{"time":1.0667,"x":60.11,"y":-168.53},{"time":1.1667,"x":16.1,"y":-8.59},{"time":2.1333,"x":60.11,"y":-168.53}],"scale":[{"x":1.318,"y":1.318},{"time":0.1},{"time":1.0667,"x":1.318,"y":1.318},{"time":1.1667},{"time":2.1333,"x":0.58,"y":0.58}]},"bone":{"rotate":[{"angle":14.5},{"time":0.5333,"angle":11},{"time":1.6,"angle":18},{"time":2.1333,"angle":14.5}],"translate":[{},{"time":1.0667,"y":37.09},{"time":2.1333}],"scale":[{},{"time":1.0667,"x":1.016,"y":1.016},{"time":2.1333}]}}}}},[0]]],0,0,[0],[-1],[0]]