[1,["b9ebCi46dHcoe8vZgCIU5A","acoUCXCA9IoolzJVex3bRr@6c48a"],["node","root","spine","data","_skeletonData"],[["cc.Prefab",["_name"],2],["cc.Node",["_name","_layer","_children","_components","_prefab"],1,2,9,4],["cc.Node",["_name","_layer","_parent","_components","_prefab"],1,1,12,4],["cc.UIOpacity",["node","__prefab"],3,1,4],["cc.CompPrefabInfo",["fileId"],2],["cc.UITransform",["node","__prefab","_contentSize"],3,1,4,5],["90fb5cRJatHw6K9trDAUdL8",["trigger","group","_shapeType","_radius","node","__prefab","spine"],-1,1,4,1],["cc.PrefabInfo",["fileId","instance","targetOverrides","nestedPrefabInstanceRoots","root","asset"],-1,1,1],["sp.Skeleton",["defaultSkin","defaultAnimation","_preCacheMode","node","__prefab"],0,1,4],["sp.SkeletonData",["_name","_atlasText","textureNames","_skeletonJson","textures"],-1,3]],[[4,0,2],[3,0,1,1],[5,0,1,2,1],[7,0,1,2,3,4,5,5],[0,0,2],[1,0,1,2,3,4,3],[2,0,1,2,3,4,3],[6,0,1,2,3,4,5,6,5],[8,0,1,2,3,4,4],[9,0,1,2,3,4,5]],[[[[4,"bullet_taijilun_0_senior"],[5,"bullet_taijilun_0_senior",1,[-6],[[1,-2,[0,"ecPaAl+GJM6InURz7yUVXY"]],[2,-3,[0,"8bN8DNCZRDlp7ze1J3ThyK"],[5,0,0]],[7,true,8,2,190,-5,[0,"81IQAbMcNJA5CPPSC6xL0l"],-4]],[3,"ddpa4hztxGmZs1/RkAUcls",null,null,null,-1,0]],[6,"skill_ctjl",1,1,[[-7,[1,-8,[0,"6bfQbBYy9KbacAKJCpplag"]],[2,-9,[0,"94yjMIwqVPhpizSpQ6p8A5"],[5,286.2,197.16]]],1,4,4],[3,"eeNB8MzdFG2oseEjig2588",null,null,null,1,0]],[8,"default","idle",0,2,[0,"50LMxaUbhNtLma+BWEgxob"]]],0,[0,1,1,0,0,1,0,0,1,0,2,3,0,0,1,0,-1,2,0,-1,3,0,0,2,0,0,2,0,3,1,9],[3],[4],[0]],[[[9,"skill_ctjl","\nskill_ctjl.png\nsize: 842, 842\nformat: RGBA8888\nfilter: Linear, Linear\nrepeat: none\nbg1\n  rotate: false\n  xy: 706, 618\n  size: 79, 79\n  orig: 79, 79\n  offset: 0, 0\n  index: -1\nbg2\n  rotate: true\n  xy: 785, 577\n  size: 60, 53\n  orig: 60, 53\n  offset: 0, 0\n  index: -1\nbg3\n  rotate: true\n  xy: 698, 461\n  size: 78, 79\n  orig: 78, 79\n  offset: 0, 0\n  index: -1\nbg4\n  rotate: true\n  xy: 777, 524\n  size: 53, 60\n  orig: 53, 60\n  offset: 0, 0\n  index: -1\nbg5\n  rotate: false\n  xy: 399, 417\n  size: 79, 78\n  orig: 79, 78\n  offset: 0, 0\n  index: -1\nbg6\n  rotate: false\n  xy: 777, 471\n  size: 60, 53\n  orig: 60, 53\n  offset: 0, 0\n  index: -1\nbg7\n  rotate: false\n  xy: 698, 539\n  size: 79, 79\n  orig: 79, 79\n  offset: 0, 0\n  index: -1\nbg8\n  rotate: false\n  xy: 785, 637\n  size: 54, 60\n  orig: 54, 60\n  offset: 0, 0\n  index: -1\nqqd\n  rotate: false\n  xy: 347, 663\n  size: 179, 179\n  orig: 179, 179\n  offset: 0, 0\n  index: -1\ntj\n  rotate: false\n  xy: 378, 18\n  size: 139, 139\n  orig: 139, 139\n  offset: 0, 0\n  index: -1\ntjbz10\n  rotate: false\n  xy: 205, 113\n  size: 173, 161\n  orig: 173, 161\n  offset: 0, 0\n  index: -1\ntjbz11\n  rotate: true\n  xy: 0, 27\n  size: 232, 205\n  orig: 232, 205\n  offset: 0, 0\n  index: -1\ntjbz12\n  rotate: true\n  xy: 0, 259\n  size: 236, 202\n  orig: 236, 202\n  offset: 0, 0\n  index: -1\ntjbz13\n  rotate: false\n  xy: 706, 697\n  size: 136, 145\n  orig: 136, 145\n  offset: 0, 0\n  index: -1\ntjbz14\n  rotate: true\n  xy: 202, 274\n  size: 221, 197\n  orig: 221, 197\n  offset: 0, 0\n  index: -1\ntjbz15\n  rotate: true\n  xy: 399, 157\n  size: 165, 174\n  orig: 165, 174\n  offset: 0, 0\n  index: -1\ntjbz16\n  rotate: true\n  xy: 657, 292\n  size: 169, 178\n  orig: 169, 178\n  offset: 0, 0\n  index: -1\ntjbz17\n  rotate: true\n  xy: 347, 495\n  size: 168, 183\n  orig: 168, 183\n  offset: 0, 0\n  index: -1\ntjbz18\n  rotate: false\n  xy: 530, 491\n  size: 168, 181\n  orig: 168, 181\n  offset: 0, 0\n  index: -1\ntjbz19\n  rotate: true\n  xy: 526, 672\n  size: 170, 180\n  orig: 170, 180\n  offset: 0, 0\n  index: -1\ntjbz20\n  rotate: true\n  xy: 478, 322\n  size: 169, 179\n  orig: 169, 179\n  offset: 0, 0\n  index: -1\ntjbz21\n  rotate: false\n  xy: 573, 132\n  size: 170, 160\n  orig: 170, 160\n  offset: 0, 0\n  index: -1\nwq\n  rotate: false\n  xy: 0, 495\n  size: 347, 347\n  orig: 347, 347\n  offset: 0, 0\n  index: -1\n",["skill_ctjl.png"],{"skeleton":{"hash":"y+pYdjDw7IY","spine":"3.8-from-4.0-from-4.1.17","x":-142.65,"y":-98.58,"width":286.2,"height":197.16},"bones":[{"name":"root","scaleX":0.45,"scaleY":0.31},{"name":"tjl","parent":"root"},{"name":"wq","parent":"tjl"},{"name":"bg","parent":"tjl"},{"name":"tj","parent":"tjl"},{"name":"qqd","parent":"tjl"},{"name":"tj2","parent":"tjl"},{"name":"tj3","parent":"tjl"},{"name":"tj4","parent":"tjl"},{"name":"tjbz","parent":"root","x":-24.27,"y":48.59},{"name":"wq2","parent":"tjl"},{"name":"wq3","parent":"tjl"},{"name":"wq4","parent":"tjl"}],"slots":[{"name":"wq","bone":"wq"},{"name":"wq4","bone":"wq4"},{"name":"wq2","bone":"wq2"},{"name":"wq3","bone":"wq3"},{"name":"qqd","bone":"qqd","attachment":"qqd"},{"name":"tj","bone":"tj","attachment":"tj"},{"name":"tj2","bone":"tj2","attachment":"tj"},{"name":"tj3","bone":"tj3","attachment":"tj"},{"name":"tj4","bone":"tj4","attachment":"tj"},{"name":"tjbz1","bone":"tjbz","blend":"additive"},{"name":"bg1","bone":"bg","attachment":"bg1"},{"name":"bg2","bone":"bg","attachment":"bg2"},{"name":"bg3","bone":"bg","attachment":"bg3"},{"name":"bg4","bone":"bg","attachment":"bg4"},{"name":"bg5","bone":"bg","attachment":"bg5"},{"name":"bg6","bone":"bg","attachment":"bg6"},{"name":"bg7","bone":"bg","attachment":"bg7"},{"name":"bg8","bone":"bg","attachment":"bg8"}],"skins":[{"name":"default","attachments":{"bg1":{"bg1":{"x":188.5,"y":-187.5,"width":157,"height":157}},"bg2":{"bg2":{"x":0.5,"y":-265,"width":119,"height":106}},"bg3":{"bg3":{"x":-187,"y":-188.5,"width":156,"height":157}},"bg4":{"bg4":{"x":-264.5,"y":-0.5,"width":105,"height":119}},"bg5":{"bg5":{"x":-187.5,"y":187,"width":157,"height":156}},"bg6":{"bg6":{"x":0.5,"y":265,"width":119,"height":106}},"bg7":{"bg7":{"x":187.5,"y":187.5,"width":157,"height":157}},"bg8":{"bg8":{"x":265.5,"y":-0.5,"width":107,"height":119}},"qqd":{"qqd":{"width":358,"height":358}},"tj":{"tj":{"y":-1,"width":278,"height":278}},"tj2":{"tj":{"y":-1,"width":278,"height":278}},"tj3":{"tj":{"y":-1,"width":278,"height":278}},"tj4":{"tj":{"y":-1,"width":278,"height":278}},"tjbz1":{"tjbz10":{"x":24.14,"y":-35.51,"width":346,"height":322},"tjbz11":{"x":35.14,"y":-61.51,"width":464,"height":410},"tjbz12":{"x":22.64,"y":-62.01,"width":471,"height":403},"tjbz13":{"x":6.64,"y":1.49,"width":271,"height":290},"tjbz14":{"x":16.64,"y":-48.51,"width":441,"height":394},"tjbz15":{"x":-11.36,"y":-24.01,"width":329,"height":347},"tjbz16":{"x":-17.36,"y":-26.51,"width":337,"height":356},"tjbz17":{"x":-16.86,"y":-24.01,"width":336,"height":365},"tjbz18":{"x":-16.86,"y":-25.01,"width":336,"height":361},"tjbz19":{"x":-14.36,"y":-23.51,"width":339,"height":360},"tjbz20":{"x":-13.86,"y":-25.51,"width":338,"height":358},"tjbz21":{"x":-15.36,"y":-45.01,"width":339,"height":319}},"wq":{"wq":{"width":694,"height":694}},"wq2":{"wq":{"width":694,"height":694}},"wq3":{"wq":{"width":694,"height":694}},"wq4":{"wq":{"width":694,"height":694}}}}],"events":{"atk":{}},"animations":{"attack":{"slots":{"bg1":{"attachment":[{"name":null}]},"bg2":{"attachment":[{"name":null}]},"bg3":{"attachment":[{"name":null}]},"bg4":{"attachment":[{"name":null}]},"bg5":{"attachment":[{"name":null}]},"bg6":{"attachment":[{"name":null}]},"bg7":{"attachment":[{"name":null}]},"bg8":{"attachment":[{"name":null}]},"qqd":{"color":[{"time":0.3333,"color":"ffffffff"},{"time":0.8,"color":"ffffff00"}]},"tj":{"color":[{"color":"ffffff00"},{"time":0.1333,"color":"ffffffff","curve":"stepped"},{"time":0.3333,"color":"ffffffff"},{"time":1.1667,"color":"ffffff00"}]},"tj2":{"color":[{"color":"ffffff00"},{"time":0.2333,"color":"ffffff8d"},{"time":0.5333,"color":"ffffff85"},{"time":0.8667,"color":"ffffff00"}],"attachment":[{"name":null}]},"tj3":{"color":[{"color":"ffffff00","curve":"stepped"},{"time":0.7667,"color":"ffffff00"},{"time":1.0667,"color":"ffffff85"},{"time":1.6333,"color":"ffffff00"}],"attachment":[{"name":null}]},"tj4":{"color":[{"color":"ffffff00"}],"attachment":[{"name":null}]},"tjbz1":{"color":[{"time":0.8667,"color":"ffffffff"},{"time":1.2,"color":"ffffff00"}],"attachment":[{"time":0.1333,"name":"tjbz10"},{"time":0.2,"name":"tjbz11"},{"time":0.2667,"name":"tjbz12"},{"time":0.3333,"name":"tjbz13"},{"time":0.4,"name":"tjbz14"},{"time":0.4667,"name":"tjbz15"},{"time":0.5333,"name":"tjbz16"},{"time":0.6,"name":"tjbz17"},{"time":0.6667,"name":"tjbz18"},{"time":0.7333,"name":"tjbz19"},{"time":0.8,"name":"tjbz20"},{"time":0.8667,"name":"tjbz21"}]},"wq":{"color":[{"color":"ffffff00"}]},"wq2":{"color":[{"color":"000000ff"},{"time":0.4,"color":"00000000"}],"attachment":[{"name":"wq"}]},"wq3":{"color":[{"color":"ffffff00"},{"time":0.2,"color":"ffffffff"},{"time":1.0333,"color":"ffffff00"}],"attachment":[{"name":"wq"}]},"wq4":{"color":[{"color":"ffffff00"}],"attachment":[{"name":"wq"}]}},"bones":{"tj":{"rotate":[{"angle":-560.66},{"time":0.3333,"angle":-706.03},{"time":1.1667,"angle":-798.08}],"scale":[{"x":0.391,"y":0.391},{"time":0.1333,"x":2.685,"y":2.685},{"time":0.3333,"x":2.869,"y":2.869}]},"qqd":{"scale":[{"x":0.057,"y":0.057},{"time":0.1333,"x":2.553,"y":2.553},{"time":0.3333,"x":2.798,"y":2.798}]},"wq":{"scale":[{"x":0.475,"y":0.475}]},"tj2":{"translate":[{"time":0.2333},{"time":0.8667,"y":589.9}]},"tj3":{"translate":[{"time":0.7667},{"time":1.6333,"y":589.9}]},"tjbz":{"translate":[{"x":25.64,"y":-4.82}],"scale":[{"x":2.434,"y":2.308}]},"wq2":{"scale":[{"x":0.047,"y":0.047},{"time":0.2,"x":1.932,"y":1.932},{"time":0.4,"x":2.165,"y":2.165}]},"wq3":{"scale":[{"x":1.245,"y":1.245},{"time":0.2,"x":1.691,"y":1.691},{"time":0.6,"x":2.04,"y":2.04}]},"wq4":{"scale":[{"x":0.475,"y":0.475}]}},"events":[{"time":0.2333,"name":"atk"}]},"idle":{"slots":{"bg1":{"color":[{"color":"ffffff00"},{"time":0.2,"color":"ffffffff","curve":"stepped"},{"time":2.2667,"color":"ffffffff"},{"time":2.6667,"color":"ffffff00"}]},"bg2":{"color":[{"color":"ffffff00"},{"time":0.2,"color":"ffffffff","curve":"stepped"},{"time":1.9,"color":"ffffffff"},{"time":2.2667,"color":"ffffff00"}]},"bg3":{"color":[{"color":"ffffff00"},{"time":0.2,"color":"ffffffff","curve":"stepped"},{"time":1.5333,"color":"ffffffff"},{"time":1.9,"color":"ffffff00"}]},"bg4":{"color":[{"color":"ffffff00"},{"time":0.2,"color":"ffffffff","curve":"stepped"},{"time":1.1333,"color":"ffffffff"},{"time":1.5333,"color":"ffffff00"}]},"bg5":{"color":[{"color":"ffffff00"},{"time":0.2,"color":"ffffffff","curve":"stepped"},{"time":0.7333,"color":"ffffffff"},{"time":1.1333,"color":"ffffff00"}]},"bg6":{"color":[{"color":"ffffff00"},{"time":0.2,"color":"ffffffff","curve":"stepped"},{"time":0.3333,"color":"ffffffff"},{"time":0.7333,"color":"ffffff00"}]},"bg7":{"color":[{"color":"ffffff00"},{"time":0.2,"color":"ffffffff","curve":"stepped"},{"time":3.0667,"color":"ffffffff"},{"time":3.4667,"color":"ffffff00"}]},"bg8":{"color":[{"color":"ffffff00"},{"time":0.2,"color":"ffffffff","curve":"stepped"},{"time":2.6667,"color":"ffffffff"},{"time":3.0667,"color":"ffffff00"}]},"qqd":{"color":[{"color":"ffffff00","curve":"stepped"},{"time":0.1,"color":"ffffff00"},{"time":0.2333,"color":"ffffffff","curve":"stepped"},{"time":3.4,"color":"ffffffff"},{"time":3.4667,"color":"ffffff00"}]},"tj":{"color":[{"color":"ffffff00"},{"time":0.2333,"color":"ffffffff","curve":"stepped"},{"time":3.4,"color":"ffffffff"},{"time":3.4667,"color":"ffffff00"}]},"tj2":{"color":[{"color":"ffffff00"},{"time":0.2333,"color":"ffffff8d"},{"time":0.5333,"color":"ffffff85"},{"time":0.8667,"color":"ffffff00"}],"attachment":[{"name":null}]},"tj3":{"color":[{"color":"ffffff00","curve":"stepped"},{"time":0.7667,"color":"ffffff00"},{"time":1.0667,"color":"ffffff85"},{"time":1.6333,"color":"ffffff00"}],"attachment":[{"name":null}]},"tj4":{"color":[{"color":"ffffff00","curve":"stepped"},{"time":1.6333,"color":"ffffff00"},{"time":1.9333,"color":"ffffff85"},{"time":2.2667,"color":"ffffff00"}],"attachment":[{"name":null}]},"wq":{"color":[{"color":"ffffff00"},{"time":3.3,"color":"ffffffeb"},{"time":3.4667,"color":"ffffff00"}],"attachment":[{"time":3.3,"name":"wq"}]},"wq2":{"color":[{"color":"000000ff"},{"time":0.2,"color":"00000000"}],"attachment":[{"name":"wq"}]},"wq3":{"color":[{"color":"ffffff00"},{"time":0.2333,"color":"ffffffff","curve":"stepped"},{"time":3.4667,"color":"ffffffff"},{"time":3.5667,"color":"ffffff00"}],"attachment":[{"name":"wq"}]},"wq4":{"color":[{"color":"ffffff00"},{"time":3.3,"color":"ffffffe5"},{"time":3.5667,"color":"ffffff00"}],"attachment":[{"time":3.4,"name":"wq"}]}},"bones":{"tj":{"rotate":[{},{"time":3.4,"angle":-560.66}],"scale":[{"time":3.4},{"time":3.4667,"x":0.391,"y":0.391}]},"qqd":{"rotate":[{},{"time":3.4,"angle":164.69}],"scale":[{},{"time":0.1,"x":0.378,"y":0.378},{"time":0.2333,"x":1.018,"y":1.018,"curve":"stepped"},{"time":3.4,"x":1.018,"y":1.018},{"time":3.4667,"x":0.469,"y":0.469}]},"wq":{"scale":[{"x":0.475,"y":0.475},{"time":3.3,"x":1.244,"y":1.244},{"time":3.4667,"x":0.035,"y":0.035}]},"tj2":{"rotate":[{},{"time":3,"angle":-560.66}],"translate":[{"time":0.2333},{"time":0.8667,"y":589.9}]},"tj3":{"rotate":[{},{"time":2.5,"angle":-560.66}],"translate":[{"time":0.7667},{"time":1.6333,"y":589.9}]},"tj4":{"rotate":[{},{"time":2.4,"angle":-560.66}],"translate":[{"time":1.6333},{"time":2.2667,"y":589.9}]},"tjbz":{"translate":[{"x":25.64,"y":-4.82}],"scale":[{"x":0.936,"y":0.7}]},"wq2":{"scale":[{"x":0.047,"y":0.047},{"time":0.1,"x":1.054,"y":1.054},{"time":0.2,"x":1.152,"y":1.152}]},"wq3":{"scale":[{"x":1.245,"y":1.245,"curve":"stepped"},{"time":3.4667,"x":1.245,"y":1.245},{"time":3.5667,"x":0.058,"y":0.058}]},"wq4":{"scale":[{"x":0.475,"y":0.475},{"time":3.4,"x":1.244,"y":1.244},{"time":3.5667,"x":-0.05,"y":-0.05}]},"bg":{"scale":[{},{"time":0.2,"x":1.131,"y":1.131}]}}}}},[0]]],0,0,[0],[-1],[1]]]]
